<?xml version="1.0" encoding="UTF-8"?>
<fpmd:species xmlns:fpmd="http://www.quantum-simulation.org/ns/fpmd/fpmd-1.0"
  xmlns:xsi="http://www.w3.org/2001/XMLSchema-instance"
  xsi:schemaLocation="http://www.quantum-simulation.org/ns/fpmd/fpmd-1.0
  species.xsd">
<description>
 PSGen-1.6.1 pseudopotential: HSCV At xc=LDA
 Generated by PSGen-1.6.1 on 2009-10-11T04:44:16Z
 psgen arguments:
 -element At -xc LDA -smooth_v -bound l=0:rc=1.60 -bound l=1:rc=1.40
 -scat l=2:rc=1.70
</description>
<symbol>At</symbol>
<atomic_number>85</atomic_number>
<mass>210</mass>
<norm_conserving_pseudopotential>
<valence_charge>7</valence_charge>
<lmax>2</lmax>
<llocal>2</llocal>
<nquad>0</nquad>
<rquad>0</rquad>
<mesh_spacing>0.01</mesh_spacing>
<projector l="0" size="1178">
<radial_potential>
4.868517
4.866699
4.861246
4.852162
4.839451
4.823123
4.803189
4.779660
4.752552
4.721883
4.687673
4.649943
4.608719
4.564028
4.515898
4.464361
4.409452
4.351207
4.289663
4.224863
4.156849
4.085668
4.011367
3.933996
3.853609
3.770260
3.684007
3.594909
3.503029
3.408431
3.311181
3.211350
3.109007
3.004228
2.897087
2.787665
2.676040
2.562297
2.446522
2.328801
2.209225
2.087887
1.964881
1.840305
1.714258
1.586842
1.458161
1.328322
1.197435
1.065609
0.932958
0.799600
0.665651
0.531233
0.396468
0.261482
0.126402
-0.008641
-0.143515
-0.278086
-0.412217
-0.545768
-0.678597
-0.810561
-0.941512
-1.071303
-1.199782
-1.326796
-1.452189
-1.575803
-1.697478
-1.817050
-1.934355
-2.049225
-2.161490
-2.270978
-2.377515
-2.480924
-2.581026
-2.677638
-2.770578
-2.859716
-2.945143
-3.027003
-3.105430
-3.180551
-3.252489
-3.321357
-3.387266
-3.450320
-3.510619
-3.568255
-3.623321
-3.675901
-3.726077
-3.773929
-3.819529
-3.862951
-3.904261
-3.943527
-3.980810
-4.016171
-4.049668
-4.081356
-4.111289
-4.139519
-4.166094
-4.191063
-4.214472
-4.236366
-4.256788
-4.275779
-4.293381
-4.309633
-4.324573
-4.338239
-4.350666
-4.361891
-4.371947
-4.380869
-4.388691
-4.395443
-4.401159
-4.405869
-4.409604
-4.412395
-4.414272
-4.415264
-4.415399
-4.414708
-4.413219
-4.410959
-4.407958
-4.404242
-4.399840
-4.394779
-4.389087
-4.382791
-4.375919
-4.368497
-4.360553
-4.352115
-4.343209
-4.333862
-4.324103
-4.313958
-4.303454
-4.292620
-4.281482
-4.270068
-4.258406
-4.246524
-4.234449
-4.222209
-4.209833
-4.197348
-4.184783
-4.172166
-4.159525
-4.146890
-4.134288
-4.121741
-4.109241
-4.096779
-4.084347
-4.071936
-4.059538
-4.047145
-4.034749
-4.022343
-4.009919
-3.997471
-3.984993
-3.972479
-3.959922
-3.947318
-3.934663
-3.921951
-3.909178
-3.896340
-3.883434
-3.870458
-3.857407
-3.844280
-3.831075
-3.817790
-3.804423
-3.790973
-3.777441
-3.763824
-3.750124
-3.736339
-3.722471
-3.708520
-3.694488
-3.680375
-3.666182
-3.651912
-3.637566
-3.623147
-3.608657
-3.594097
-3.579472
-3.564784
-3.550036
-3.535231
-3.520372
-3.505464
-3.490509
-3.475511
-3.460475
-3.445403
-3.430301
-3.415172
-3.400020
-3.384849
-3.369664
-3.354469
-3.339269
-3.324066
-3.308867
-3.293675
-3.278494
-3.263329
-3.248184
-3.233063
-3.217970
-3.202910
-3.187886
-3.172903
-3.157964
-3.143073
-3.128235
-3.113452
-3.098729
-3.084069
-3.069474
-3.054950
-3.040498
-3.026122
-3.011825
-2.997610
-2.983479
-2.969435
-2.955480
-2.941618
-2.927850
-2.914177
-2.900603
-2.887130
-2.873758
-2.860489
-2.847325
-2.834268
-2.821318
-2.808477
-2.795745
-2.783123
-2.770613
-2.758215
-2.745929
-2.733755
-2.721695
-2.709747
-2.697913
-2.686193
-2.674585
-2.663090
-2.651708
-2.640438
-2.629280
-2.618233
-2.607297
-2.596470
-2.585753
-2.575144
-2.564642
-2.554247
-2.543958
-2.533772
-2.523690
-2.513710
-2.503831
-2.494052
-2.484372
-2.474788
-2.465301
-2.455908
-2.446608
-2.437400
-2.428283
-2.419255
-2.410314
-2.401460
-2.392691
-2.384005
-2.375402
-2.366879
-2.358435
-2.350070
-2.341781
-2.333567
-2.325427
-2.317360
-2.309364
-2.301437
-2.293580
-2.285790
-2.278066
-2.270407
-2.262812
-2.255279
-2.247808
-2.240397
-2.233045
-2.225752
-2.218515
-2.211335
-2.204210
-2.197138
-2.190120
-2.183154
-2.176240
-2.169376
-2.162561
-2.155796
-2.149078
-2.142407
-2.135783
-2.129204
-2.122671
-2.116182
-2.109736
-2.103333
-2.096973
-2.090654
-2.084377
-2.078140
-2.071943
-2.065785
-2.059667
-2.053586
-2.047544
-2.041539
-2.035571
-2.029639
-2.023744
-2.017884
-2.012060
-2.006270
-2.000515
-1.994793
-1.989106
-1.983452
-1.977830
-1.972242
-1.966685
-1.961161
-1.955668
-1.950206
-1.944776
-1.939376
-1.934006
-1.928667
-1.923357
-1.918077
-1.912827
-1.907605
-1.902412
-1.897248
-1.892112
-1.887004
-1.881923
-1.876870
-1.871845
-1.866846
-1.861875
-1.856930
-1.852011
-1.847119
-1.842252
-1.837411
-1.832596
-1.827806
-1.823041
-1.818301
-1.813586
-1.808895
-1.804228
-1.799586
-1.794968
-1.790373
-1.785802
-1.781254
-1.776730
-1.772228
-1.767750
-1.763293
-1.758860
-1.754449
-1.750060
-1.745693
-1.741347
-1.737024
-1.732721
-1.728441
-1.724181
-1.719942
-1.715724
-1.711527
-1.707351
-1.703194
-1.699058
-1.694942
-1.690846
-1.686770
-1.682714
-1.678677
-1.674659
-1.670661
-1.666681
-1.662721
-1.658779
-1.654856
-1.650952
-1.647066
-1.643198
-1.639349
-1.635517
-1.631704
-1.627908
-1.624130
-1.620369
-1.616626
-1.612900
-1.609191
-1.605500
-1.601825
-1.598167
-1.594525
-1.590901
-1.587292
-1.583700
-1.580125
-1.576565
-1.573022
-1.569494
-1.565982
-1.562486
-1.559005
-1.555540
-1.552091
-1.548656
-1.545237
-1.541833
-1.538444
-1.535070
-1.531710
-1.528365
-1.525035
-1.521720
-1.518418
-1.515131
-1.511858
-1.508600
-1.505355
-1.502124
-1.498908
-1.495704
-1.492515
-1.489339
-1.486177
-1.483028
-1.479892
-1.476770
-1.473661
-1.470565
-1.467481
-1.464411
-1.461354
-1.458309
-1.455277
-1.452258
-1.449251
-1.446256
-1.443274
-1.440304
-1.437347
-1.434401
-1.431468
-1.428546
-1.425637
-1.422739
-1.419853
-1.416979
-1.414116
-1.411265
-1.408425
-1.405597
-1.402780
-1.399975
-1.397180
-1.394397
-1.391625
-1.388863
-1.386113
-1.383374
-1.380645
-1.377927
-1.375220
-1.372524
-1.369838
-1.367162
-1.364497
-1.361842
-1.359198
-1.356564
-1.353940
-1.351326
-1.348723
-1.346129
-1.343545
-1.340971
-1.338407
-1.335853
-1.333309
-1.330774
-1.328249
-1.325733
-1.323227
-1.320730
-1.318243
-1.315765
-1.313297
-1.310837
-1.308387
-1.305946
-1.303514
-1.301092
-1.298678
-1.296273
-1.293877
-1.291490
-1.289111
-1.286741
-1.284381
-1.282028
-1.279685
-1.277349
-1.275023
-1.272705
-1.270395
-1.268093
-1.265800
-1.263516
-1.261239
-1.258971
-1.256710
-1.254458
-1.252214
-1.249978
-1.247750
-1.245530
-1.243318
-1.241113
-1.238917
-1.236728
-1.234547
-1.232373
-1.230207
-1.228049
-1.225899
-1.223756
-1.221620
-1.219492
-1.217371
-1.215257
-1.213151
-1.211053
-1.208961
-1.206877
-1.204799
-1.202729
-1.200666
-1.198611
-1.196562
-1.194520
-1.192485
-1.190457
-1.188436
-1.186422
-1.184414
-1.182414
-1.180420
-1.178432
-1.176452
-1.174478
-1.172511
-1.170550
-1.168596
-1.166648
-1.164707
-1.162773
-1.160844
-1.158923
-1.157007
-1.155098
-1.153195
-1.151298
-1.149408
-1.147524
-1.145646
-1.143774
-1.141908
-1.140048
-1.138194
-1.136347
-1.134505
-1.132669
-1.130840
-1.129016
-1.127198
-1.125386
-1.123579
-1.121779
-1.119984
-1.118195
-1.116412
-1.114634
-1.112862
-1.111095
-1.109335
-1.107579
-1.105830
-1.104086
-1.102347
-1.100614
-1.098886
-1.097164
-1.095447
-1.093735
-1.092029
-1.090328
-1.088632
-1.086942
-1.085257
-1.083577
-1.081902
-1.080233
-1.078568
-1.076909
-1.075255
-1.073606
-1.071962
-1.070323
-1.068688
-1.067059
-1.065435
-1.063816
-1.062202
-1.060593
-1.058988
-1.057388
-1.055794
-1.054204
-1.052618
-1.051038
-1.049462
-1.047891
-1.046325
-1.044763
-1.043206
-1.041654
-1.040106
-1.038563
-1.037025
-1.035491
-1.033961
-1.032436
-1.030916
-1.029400
-1.027888
-1.026381
-1.024878
-1.023380
-1.021886
-1.020396
-1.018911
-1.017430
-1.015954
-1.014481
-1.013013
-1.011549
-1.010090
-1.008634
-1.007183
-1.005736
-1.004293
-1.002854
-1.001420
-0.999989
-0.998563
-0.997140
-0.995722
-0.994307
-0.992897
-0.991491
-0.990088
-0.988690
-0.987296
-0.985905
-0.984518
-0.983136
-0.981757
-0.980382
-0.979011
-0.977643
-0.976280
-0.974920
-0.973564
-0.972212
-0.970864
-0.969519
-0.968178
-0.966841
-0.965508
-0.964178
-0.962851
-0.961529
-0.960210
-0.958895
-0.957583
-0.956275
-0.954970
-0.953669
-0.952372
-0.951078
-0.949787
-0.948500
-0.947217
-0.945937
-0.944660
-0.943387
-0.942118
-0.940851
-0.939589
-0.938329
-0.937073
-0.935820
-0.934571
-0.933325
-0.932082
-0.930843
-0.929606
-0.928374
-0.927144
-0.925918
-0.924695
-0.923475
-0.922258
-0.921045
-0.919834
-0.918627
-0.917423
-0.916222
-0.915025
-0.913830
-0.912639
-0.911451
-0.910265
-0.909083
-0.907904
-0.906728
-0.905555
-0.904385
-0.903218
-0.902054
-0.900893
-0.899736
-0.898581
-0.897429
-0.896280
-0.895133
-0.893990
-0.892850
-0.891713
-0.890578
-0.889447
-0.888318
-0.887192
-0.886069
-0.884949
-0.883831
-0.882717
-0.881605
-0.880496
-0.879390
-0.878287
-0.877186
-0.876088
-0.874993
-0.873901
-0.872811
-0.871724
-0.870640
-0.869559
-0.868480
-0.867404
-0.866330
-0.865259
-0.864191
-0.863126
-0.862063
-0.861002
-0.859945
-0.858890
-0.857837
-0.856787
-0.855740
-0.854695
-0.853653
-0.852613
-0.851576
-0.850541
-0.849509
-0.848479
-0.847452
-0.846427
-0.845405
-0.844385
-0.843368
-0.842353
-0.841341
-0.840331
-0.839323
-0.838318
-0.837315
-0.836315
-0.835317
-0.834321
-0.833328
-0.832337
-0.831349
-0.830362
-0.829379
-0.828397
-0.827418
-0.826441
-0.825466
-0.824494
-0.823524
-0.822557
-0.821591
-0.820628
-0.819667
-0.818708
-0.817752
-0.816798
-0.815846
-0.814896
-0.813949
-0.813003
-0.812060
-0.811119
-0.810180
-0.809244
-0.808309
-0.807377
-0.806447
-0.805519
-0.804593
-0.803669
-0.802748
-0.801828
-0.800911
-0.799995
-0.799082
-0.798171
-0.797262
-0.796355
-0.795450
-0.794547
-0.793646
-0.792748
-0.791851
-0.790956
-0.790063
-0.789173
-0.788284
-0.787397
-0.786513
-0.785630
-0.784749
-0.783870
-0.782994
-0.782119
-0.781246
-0.780375
-0.779506
-0.778639
-0.777774
-0.776911
-0.776049
-0.775190
-0.774332
-0.773477
-0.772623
-0.771771
-0.770921
-0.770073
-0.769227
-0.768383
-0.767540
-0.766699
-0.765861
-0.765024
-0.764188
-0.763355
-0.762524
-0.761694
-0.760866
-0.760040
-0.759215
-0.758393
-0.757572
-0.756753
-0.755936
-0.755121
-0.754307
-0.753495
-0.752685
-0.751876
-0.751070
-0.750265
-0.749461
-0.748660
-0.747860
-0.747062
-0.746265
-0.745471
-0.744678
-0.743886
-0.743097
-0.742309
-0.741522
-0.740738
-0.739955
-0.739173
-0.738393
-0.737615
-0.736839
-0.736064
-0.735291
-0.734519
-0.733750
-0.732981
-0.732215
-0.731449
-0.730686
-0.729924
-0.729164
-0.728405
-0.727648
-0.726892
-0.726138
-0.725386
-0.724635
-0.723885
-0.723138
-0.722391
-0.721647
-0.720903
-0.720162
-0.719422
-0.718683
-0.717946
-0.717210
-0.716476
-0.715744
-0.715013
-0.714283
-0.713555
-0.712828
-0.712103
-0.711379
-0.710657
-0.709937
-0.709217
-0.708499
-0.707783
-0.707068
-0.706355
-0.705643
-0.704932
-0.704223
-0.703515
-0.702809
-0.702104
-0.701400
-0.700698
-0.699998
-0.699298
-0.698600
-0.697904
-0.697209
-0.696515
-0.695823
-0.695132
-0.694442
-0.693754
-0.693067
-0.692381
-0.691697
-0.691014
-0.690333
-0.689653
-0.688974
-0.688297
-0.687621
-0.686946
-0.686272
-0.685600
-0.684929
-0.684260
-0.683592
-0.682925
-0.682259
-0.681595
-0.680932
-0.680270
-0.679610
-0.678950
-0.678292
-0.677636
-0.676981
-0.676326
-0.675674
-0.675022
-0.674372
-0.673723
-0.673075
-0.672428
-0.671783
-0.671139
-0.670496
-0.669855
-0.669214
-0.668575
-0.667937
-0.667300
-0.666665
-0.666030
-0.665397
-0.664765
-0.664135
-0.663505
-0.662877
-0.662250
-0.661624
-0.660999
-0.660376
-0.659753
-0.659132
-0.658512
-0.657893
-0.657275
-0.656659
-0.656043
-0.655429
-0.654816
-0.654204
-0.653593
-0.652983
-0.652375
-0.651767
-0.651161
-0.650556
-0.649952
-0.649349
-0.648747
-0.648147
-0.647547
-0.646948
-0.646351
-0.645755
-0.645160
-0.644566
-0.643973
-0.643381
-0.642790
-0.642200
-0.641612
-0.641024
-0.640438
-0.639852
-0.639268
-0.638685
-0.638102
-0.637521
-0.636941
-0.636362
-0.635784
-0.635207
-0.634631
-0.634057
-0.633483
-0.632910
-0.632338
-0.631768
-0.631198
-0.630629
-0.630062
-0.629495
-0.628929
-0.628365
-0.627801
-0.627239
-0.626677
-0.626117
-0.625557
-0.624999
-0.624441
-0.623885
-0.623329
-0.622774
-0.622221
-0.621668
-0.621117
-0.620566
-0.620016
-0.619468
-0.618920
-0.618373
-0.617828
-0.617283
-0.616739
-0.616196
-0.615654
-0.615113
-0.614573
-0.614034
-0.613496
-0.612959
-0.612422
-0.611887
-0.611353
-0.610819
-0.610287
-0.609755
-0.609224
-0.608695
-0.608166
-0.607638
-0.607111
-0.606585
-0.606059
-0.605535
-0.605012
-0.604489
-0.603968
-0.603447
-0.602927
-0.602409
-0.601891
-0.601374
-0.600857
-0.600342
-0.599828
-0.599314
-0.598801
-0.598290
-0.597779
-0.597269
-0.596759
-0.596251
-0.595744
-0.595237
-0.594731
</radial_potential>
<radial_function>
3.920772e-02
3.928694e-02
3.952461e-02
3.992056e-02
4.047451e-02
4.118610e-02
4.205484e-02
4.308016e-02
4.426135e-02
4.559764e-02
4.708813e-02
4.873180e-02
5.052756e-02
5.247421e-02
5.457042e-02
5.681481e-02
5.920584e-02
6.174193e-02
6.442137e-02
6.724234e-02
7.020297e-02
7.330125e-02
7.653511e-02
7.990238e-02
8.340078e-02
8.702796e-02
9.078150e-02
9.465886e-02
9.865745e-02
1.027746e-01
1.070074e-01
1.113533e-01
1.158091e-01
1.203719e-01
1.250387e-01
1.298063e-01
1.346715e-01
1.396311e-01
1.446817e-01
1.498200e-01
1.550425e-01
1.603457e-01
1.657261e-01
1.711801e-01
1.767040e-01
1.822943e-01
1.879470e-01
1.936586e-01
1.994252e-01
2.052430e-01
2.111081e-01
2.170166e-01
2.229648e-01
2.289485e-01
2.349640e-01
2.410073e-01
2.470745e-01
2.531615e-01
2.592644e-01
2.653793e-01
2.715022e-01
2.776292e-01
2.837564e-01
2.898797e-01
2.959955e-01
3.020996e-01
3.081884e-01
3.142580e-01
3.203046e-01
3.263244e-01
3.323138e-01
3.382690e-01
3.441864e-01
3.500624e-01
3.558936e-01
3.616764e-01
3.674073e-01
3.730832e-01
3.787005e-01
3.842562e-01
3.897470e-01
3.951698e-01
4.005217e-01
4.057996e-01
4.110008e-01
4.161224e-01
4.211616e-01
4.261160e-01
4.309830e-01
4.357600e-01
4.404448e-01
4.450352e-01
4.495288e-01
4.539238e-01
4.582180e-01
4.624096e-01
4.664969e-01
4.704782e-01
4.743518e-01
4.781163e-01
4.817703e-01
4.853126e-01
4.887420e-01
4.920573e-01
4.952578e-01
4.983424e-01
5.013105e-01
5.041613e-01
5.068943e-01
5.095092e-01
5.120054e-01
5.143827e-01
5.166411e-01
5.187804e-01
5.208006e-01
5.227020e-01
5.244847e-01
5.261490e-01
5.276953e-01
5.291242e-01
5.304361e-01
5.316319e-01
5.327121e-01
5.336777e-01
5.345295e-01
5.352684e-01
5.358956e-01
5.364122e-01
5.368193e-01
5.371181e-01
5.373101e-01
5.373964e-01
5.373787e-01
5.372582e-01
5.370366e-01
5.367154e-01
5.362962e-01
5.357807e-01
5.351705e-01
5.344674e-01
5.336731e-01
5.327894e-01
5.318181e-01
5.307611e-01
5.296200e-01
5.283970e-01
5.270936e-01
5.257120e-01
5.242539e-01
5.227212e-01
5.211158e-01
5.194396e-01
5.176945e-01
5.158823e-01
5.140048e-01
5.120639e-01
5.100615e-01
5.079993e-01
5.058790e-01
5.037025e-01
5.014714e-01
4.991875e-01
4.968523e-01
4.944675e-01
4.920347e-01
4.895555e-01
4.870313e-01
4.844638e-01
4.818543e-01
4.792043e-01
4.765153e-01
4.737887e-01
4.710258e-01
4.682280e-01
4.653968e-01
4.625333e-01
4.596390e-01
4.567150e-01
4.537628e-01
4.507834e-01
4.477783e-01
4.447486e-01
4.416954e-01
4.386201e-01
4.355238e-01
4.324076e-01
4.292727e-01
4.261202e-01
4.229513e-01
4.197670e-01
4.165684e-01
4.133567e-01
4.101328e-01
4.068978e-01
4.036528e-01
4.003987e-01
3.971366e-01
3.938674e-01
3.905921e-01
3.873117e-01
3.840272e-01
3.807393e-01
3.774491e-01
3.741574e-01
3.708652e-01
3.675732e-01
3.642824e-01
3.609935e-01
3.577074e-01
3.544248e-01
3.511466e-01
3.478735e-01
3.446063e-01
3.413457e-01
3.380924e-01
3.348470e-01
3.316104e-01
3.283831e-01
3.251658e-01
3.219592e-01
3.187637e-01
3.155801e-01
3.124089e-01
3.092506e-01
3.061058e-01
3.029751e-01
2.998589e-01
2.967576e-01
2.936719e-01
2.906022e-01
2.875488e-01
2.845122e-01
2.814928e-01
2.784910e-01
2.755072e-01
2.725417e-01
2.695949e-01
2.666671e-01
2.637585e-01
2.608695e-01
2.580004e-01
2.551515e-01
2.523228e-01
2.495148e-01
2.467276e-01
2.439615e-01
2.412165e-01
2.384929e-01
2.357909e-01
2.331106e-01
2.304521e-01
2.278155e-01
2.252011e-01
2.226088e-01
2.200387e-01
2.174910e-01
2.149657e-01
2.124629e-01
2.099826e-01
2.075248e-01
2.050895e-01
2.026769e-01
2.002868e-01
1.979193e-01
1.955744e-01
1.932520e-01
1.909522e-01
1.886748e-01
1.864199e-01
1.841874e-01
1.819772e-01
1.797892e-01
1.776235e-01
1.754799e-01
1.733583e-01
1.712587e-01
1.691810e-01
1.671250e-01
1.650906e-01
1.630778e-01
1.610865e-01
1.591165e-01
1.571676e-01
1.552399e-01
1.533331e-01
1.514471e-01
1.495818e-01
1.477370e-01
1.459127e-01
1.441086e-01
1.423246e-01
1.405606e-01
1.388164e-01
1.370919e-01
1.353869e-01
1.337012e-01
1.320348e-01
1.303874e-01
1.287589e-01
1.271492e-01
1.255580e-01
1.239852e-01
1.224307e-01
1.208942e-01
1.193757e-01
1.178749e-01
1.163918e-01
1.149260e-01
1.134776e-01
1.120462e-01
1.106318e-01
1.092341e-01
1.078531e-01
1.064885e-01
1.051402e-01
1.038080e-01
1.024918e-01
1.011914e-01
9.990664e-02
9.863734e-02
9.738336e-02
9.614453e-02
9.492071e-02
9.371173e-02
9.251743e-02
9.133767e-02
9.017227e-02
8.902110e-02
8.788399e-02
8.676080e-02
8.565137e-02
8.455555e-02
8.347319e-02
8.240415e-02
8.134827e-02
8.030542e-02
7.927544e-02
7.825819e-02
7.725353e-02
7.626132e-02
7.528141e-02
7.431367e-02
7.335796e-02
7.241414e-02
7.148207e-02
7.056162e-02
6.965266e-02
6.875506e-02
6.786867e-02
6.699338e-02
6.612906e-02
6.527557e-02
6.443278e-02
6.360059e-02
6.277885e-02
6.196745e-02
6.116626e-02
6.037517e-02
5.959406e-02
5.882280e-02
5.806128e-02
5.730938e-02
5.656700e-02
5.583400e-02
5.511030e-02
5.439576e-02
5.369029e-02
5.299376e-02
5.230609e-02
5.162715e-02
5.095684e-02
5.029506e-02
4.964171e-02
4.899668e-02
4.835987e-02
4.773118e-02
4.711051e-02
4.649777e-02
4.589285e-02
4.529567e-02
4.470612e-02
4.412411e-02
4.354956e-02
4.298236e-02
4.242243e-02
4.186968e-02
4.132402e-02
4.078536e-02
4.025361e-02
3.972870e-02
3.921053e-02
3.869902e-02
3.819409e-02
3.769566e-02
3.720364e-02
3.671796e-02
3.623853e-02
3.576529e-02
3.529814e-02
3.483702e-02
3.438185e-02
3.393255e-02
3.348906e-02
3.305129e-02
3.261918e-02
3.219266e-02
3.177165e-02
3.135608e-02
3.094590e-02
3.054102e-02
3.014138e-02
2.974692e-02
2.935757e-02
2.897327e-02
2.859395e-02
2.821954e-02
2.785000e-02
2.748525e-02
2.712523e-02
2.676988e-02
2.641915e-02
2.607298e-02
2.573130e-02
2.539407e-02
2.506121e-02
2.473269e-02
2.440844e-02
2.408841e-02
2.377254e-02
2.346078e-02
2.315308e-02
2.284939e-02
2.254965e-02
2.225382e-02
2.196184e-02
2.167367e-02
2.138925e-02
2.110855e-02
2.083150e-02
2.055807e-02
2.028820e-02
2.002186e-02
1.975899e-02
1.949956e-02
1.924351e-02
1.899081e-02
1.874140e-02
1.849526e-02
1.825233e-02
1.801257e-02
1.777595e-02
1.754242e-02
1.731195e-02
1.708449e-02
1.686000e-02
1.663845e-02
1.641980e-02
1.620401e-02
1.599105e-02
1.578087e-02
1.557344e-02
1.536873e-02
1.516670e-02
1.496732e-02
1.477054e-02
1.457635e-02
1.438470e-02
1.419556e-02
1.400890e-02
1.382468e-02
1.364288e-02
1.346347e-02
1.328640e-02
1.311166e-02
1.293921e-02
1.276902e-02
1.260107e-02
1.243531e-02
1.227174e-02
1.211030e-02
1.195099e-02
1.179377e-02
1.163861e-02
1.148549e-02
1.133438e-02
1.118525e-02
1.103808e-02
1.089284e-02
1.074951e-02
1.060807e-02
1.046848e-02
1.033072e-02
1.019478e-02
1.006062e-02
9.928220e-03
9.797563e-03
9.668624e-03
9.541378e-03
9.415806e-03
9.291884e-03
9.169591e-03
9.048905e-03
8.929807e-03
8.812274e-03
8.696287e-03
8.581825e-03
8.468868e-03
8.357397e-03
8.247392e-03
8.138834e-03
8.031704e-03
7.925983e-03
7.821653e-03
7.718696e-03
7.617093e-03
7.516828e-03
7.417881e-03
7.320237e-03
7.223877e-03
7.128786e-03
7.034946e-03
6.942342e-03
6.850956e-03
6.760773e-03
6.671777e-03
6.583953e-03
6.497285e-03
6.411758e-03
6.327357e-03
6.244067e-03
6.161874e-03
6.080763e-03
6.000720e-03
5.921731e-03
5.843783e-03
5.766861e-03
5.690951e-03
5.616042e-03
5.542119e-03
5.469170e-03
5.397181e-03
5.326141e-03
5.256037e-03
5.186855e-03
5.118586e-03
5.051215e-03
4.984732e-03
4.919125e-03
4.854382e-03
4.790491e-03
4.727443e-03
4.665225e-03
4.603827e-03
4.543238e-03
4.483447e-03
4.424444e-03
4.366218e-03
4.308760e-03
4.252058e-03
4.196104e-03
4.140887e-03
4.086397e-03
4.032626e-03
3.979563e-03
3.927199e-03
3.875525e-03
3.824532e-03
3.774211e-03
3.724553e-03
3.675550e-03
3.627192e-03
3.579472e-03
3.532380e-03
3.485909e-03
3.440050e-03
3.394796e-03
3.350138e-03
3.306068e-03
3.262579e-03
3.219664e-03
3.177314e-03
3.135522e-03
3.094280e-03
3.053582e-03
3.013421e-03
2.973789e-03
2.934679e-03
2.896084e-03
2.857998e-03
2.820414e-03
2.783325e-03
2.746725e-03
2.710607e-03
2.674965e-03
2.639793e-03
2.605084e-03
2.570833e-03
2.537033e-03
2.503678e-03
2.470763e-03
2.438282e-03
2.406229e-03
2.374597e-03
2.343383e-03
2.312580e-03
2.282183e-03
2.252187e-03
2.222585e-03
2.193374e-03
2.164547e-03
2.136101e-03
2.108029e-03
2.080327e-03
2.052989e-03
2.026013e-03
1.999391e-03
1.973120e-03
1.947195e-03
1.921612e-03
1.896366e-03
1.871452e-03
1.846867e-03
1.822605e-03
1.798663e-03
1.775037e-03
1.751721e-03
1.728713e-03
1.706007e-03
1.683601e-03
1.661490e-03
1.639670e-03
1.618138e-03
1.596889e-03
1.575919e-03
1.555226e-03
1.534806e-03
1.514654e-03
1.494768e-03
1.475144e-03
1.455778e-03
1.436667e-03
1.417808e-03
1.399197e-03
1.380831e-03
1.362707e-03
1.344821e-03
1.327171e-03
1.309753e-03
1.292565e-03
1.275603e-03
1.258864e-03
1.242346e-03
1.226045e-03
1.209958e-03
1.194083e-03
1.178418e-03
1.162958e-03
1.147702e-03
1.132646e-03
1.117789e-03
1.103128e-03
1.088659e-03
1.074380e-03
1.060290e-03
1.046385e-03
1.032663e-03
1.019121e-03
1.005758e-03
9.925701e-04
9.795561e-04
9.667132e-04
9.540393e-04
9.415321e-04
9.291894e-04
9.170091e-04
9.049890e-04
8.931270e-04
8.814210e-04
8.698689e-04
8.584688e-04
8.472187e-04
8.361164e-04
8.251602e-04
8.143480e-04
8.036781e-04
7.931484e-04
7.827571e-04
7.725025e-04
7.623827e-04
7.523959e-04
7.425405e-04
7.328146e-04
7.232165e-04
7.137446e-04
7.043972e-04
6.951727e-04
6.860694e-04
6.770857e-04
6.682201e-04
6.594711e-04
6.508369e-04
6.423163e-04
6.339076e-04
6.256094e-04
6.174202e-04
6.093387e-04
6.013633e-04
5.934926e-04
5.857254e-04
5.780602e-04
5.704957e-04
5.630306e-04
5.556635e-04
5.483931e-04
5.412183e-04
5.341377e-04
5.271500e-04
5.202541e-04
5.134488e-04
5.067329e-04
5.001051e-04
4.935643e-04
4.871094e-04
4.807393e-04
4.744527e-04
4.682487e-04
4.621262e-04
4.560840e-04
4.501211e-04
4.442365e-04
4.384291e-04
4.326979e-04
4.270419e-04
4.214602e-04
4.159517e-04
4.105154e-04
4.051505e-04
3.998560e-04
3.946310e-04
3.894745e-04
3.843856e-04
3.793635e-04
3.744073e-04
3.695161e-04
3.646890e-04
3.599252e-04
3.552240e-04
3.505843e-04
3.460055e-04
3.414868e-04
3.370273e-04
3.326262e-04
3.282829e-04
3.239965e-04
3.197663e-04
3.155916e-04
3.114716e-04
3.074055e-04
3.033928e-04
2.994327e-04
2.955245e-04
2.916674e-04
2.878610e-04
2.841044e-04
2.803970e-04
2.767382e-04
2.731274e-04
2.695638e-04
2.660470e-04
2.625762e-04
2.591508e-04
2.557704e-04
2.524342e-04
2.491417e-04
2.458923e-04
2.426855e-04
2.395207e-04
2.363973e-04
2.333148e-04
2.302727e-04
2.272704e-04
2.243074e-04
2.213832e-04
2.184973e-04
2.156492e-04
2.128383e-04
2.100642e-04
2.073265e-04
2.046245e-04
2.019580e-04
1.993263e-04
1.967290e-04
1.941658e-04
1.916361e-04
1.891394e-04
1.866755e-04
1.842437e-04
1.818438e-04
1.794753e-04
1.771377e-04
1.748307e-04
1.725539e-04
1.703069e-04
1.680892e-04
1.659006e-04
1.637406e-04
1.616088e-04
1.595048e-04
1.574284e-04
1.553792e-04
1.533567e-04
1.513606e-04
1.493907e-04
1.474465e-04
1.455277e-04
1.436339e-04
1.417650e-04
1.399204e-04
1.381000e-04
1.363033e-04
1.345301e-04
1.327801e-04
1.310529e-04
1.293483e-04
1.276660e-04
1.260056e-04
1.243669e-04
1.227496e-04
1.211535e-04
1.195782e-04
1.180234e-04
1.164890e-04
1.149746e-04
1.134799e-04
1.120048e-04
1.105490e-04
1.091121e-04
1.076940e-04
1.062944e-04
1.049131e-04
1.035497e-04
1.022042e-04
1.008763e-04
9.956565e-05
9.827213e-05
9.699548e-05
9.573548e-05
9.449193e-05
9.326459e-05
9.205327e-05
9.085775e-05
8.967781e-05
8.851327e-05
8.736392e-05
8.622955e-05
8.510998e-05
8.400500e-05
8.291443e-05
8.183808e-05
8.077576e-05
7.972729e-05
7.869249e-05
7.767118e-05
7.666317e-05
7.566831e-05
7.468641e-05
7.371731e-05
7.276084e-05
7.181682e-05
7.088511e-05
6.996554e-05
6.905795e-05
6.816218e-05
6.727809e-05
6.640550e-05
6.554429e-05
6.469429e-05
6.385536e-05
6.302736e-05
6.221014e-05
6.140356e-05
6.060748e-05
5.982177e-05
5.904629e-05
5.828090e-05
5.752548e-05
5.677989e-05
5.604400e-05
5.531770e-05
5.460084e-05
5.389332e-05
5.319500e-05
5.250577e-05
5.182551e-05
5.115410e-05
5.049143e-05
4.983737e-05
4.919183e-05
4.855468e-05
4.792582e-05
4.730514e-05
4.669254e-05
4.608790e-05
4.549112e-05
4.490210e-05
4.432075e-05
4.374695e-05
4.318061e-05
4.262164e-05
4.206993e-05
4.152539e-05
4.098793e-05
4.045746e-05
3.993389e-05
3.941711e-05
3.890706e-05
3.840363e-05
3.790674e-05
3.741631e-05
3.693225e-05
3.645449e-05
3.598292e-05
3.551749e-05
3.505810e-05
3.460467e-05
3.415714e-05
3.371542e-05
3.327943e-05
3.284911e-05
3.242438e-05
3.200516e-05
3.159138e-05
3.118298e-05
3.077987e-05
3.038200e-05
2.998930e-05
2.960169e-05
2.921912e-05
2.884151e-05
2.846880e-05
2.810092e-05
2.773782e-05
2.737943e-05
2.702570e-05
2.667655e-05
2.633193e-05
2.599178e-05
2.565605e-05
2.532467e-05
2.499758e-05
2.467475e-05
2.435609e-05
2.404157e-05
2.373113e-05
2.342471e-05
2.312227e-05
2.282375e-05
2.252910e-05
2.223827e-05
2.195120e-05
2.166786e-05
2.138820e-05
2.111215e-05
2.083969e-05
2.057075e-05
2.030531e-05
2.004330e-05
1.978468e-05
1.952942e-05
1.927746e-05
1.902877e-05
1.878330e-05
1.854101e-05
1.830186e-05
1.806580e-05
1.783281e-05
1.760283e-05
1.737582e-05
1.715176e-05
1.693060e-05
1.671231e-05
1.649683e-05
1.628415e-05
1.607423e-05
1.586702e-05
1.566249e-05
1.546061e-05
1.526134e-05
1.506465e-05
1.487051e-05
1.467888e-05
1.448972e-05
1.430302e-05
1.411873e-05
1.393683e-05
1.375728e-05
1.358005e-05
1.340512e-05
1.323244e-05
1.306200e-05
1.289377e-05
1.272771e-05
1.256380e-05
1.240201e-05
1.224231e-05
1.208467e-05
1.192907e-05
1.177549e-05
1.162389e-05
1.147425e-05
1.132654e-05
1.118075e-05
1.103683e-05
1.089478e-05
1.075457e-05
1.061616e-05
1.047954e-05
1.034469e-05
1.021159e-05
1.008020e-05
9.950505e-06
9.822489e-06
9.696127e-06
9.571397e-06
9.448277e-06
9.326748e-06
9.206789e-06
9.088379e-06
8.971497e-06
8.856125e-06
8.742243e-06
8.629831e-06
8.518870e-06
8.409342e-06
8.301228e-06
8.194509e-06
8.089167e-06
7.985186e-06
7.882546e-06
7.781231e-06
7.681223e-06
7.582506e-06
7.485063e-06
7.388877e-06
7.293932e-06
7.200212e-06
7.107700e-06
7.016383e-06
6.926243e-06
6.837266e-06
6.749436e-06
6.662739e-06
6.577160e-06
6.492685e-06
6.409299e-06
6.326988e-06
6.245739e-06
6.165537e-06
6.086369e-06
6.008222e-06
5.931082e-06
5.854936e-06
5.779772e-06
5.705576e-06
5.632337e-06
5.560041e-06
5.488678e-06
5.418233e-06
5.348697e-06
5.280056e-06
5.212300e-06
5.145417e-06
5.079395e-06
5.014223e-06
4.949892e-06
4.886388e-06
4.823703e-06
4.761825e-06
4.700744e-06
4.640449e-06
4.580931e-06
4.522179e-06
4.464184e-06
4.406935e-06
4.350423e-06
4.294639e-06
4.239573e-06
4.185215e-06
4.131558e-06
4.078591e-06
4.026305e-06
3.974693e-06
3.923744e-06
3.873451e-06
3.823806e-06
3.774799e-06
3.726422e-06
3.678668e-06
3.631529e-06
3.584995e-06
3.539061e-06
3.493717e-06
3.448956e-06
3.404771e-06
3.361154e-06
3.318098e-06
3.275596e-06
3.233640e-06
3.192223e-06
3.151340e-06
3.110981e-06
3.071142e-06
3.031814e-06
2.992993e-06
2.954670e-06
2.916840e-06
2.879496e-06
2.842631e-06
2.806241e-06
2.770318e-06
2.734857e-06
2.699852e-06
2.665296e-06
2.631184e-06
2.597510e-06
2.564269e-06
2.531455e-06
2.499063e-06
2.467086e-06
2.435520e-06
2.404360e-06
2.373600e-06
2.343234e-06
2.313259e-06
2.283668e-06
2.254458e-06
2.225622e-06
2.197157e-06
2.169057e-06
2.141318e-06
2.113935e-06
2.086903e-06
2.060219e-06
2.033876e-06
2.007872e-06
1.982202e-06
1.956861e-06
1.931845e-06
1.907150e-06
1.882772e-06
1.858707e-06
1.834950e-06
1.811498e-06
1.788347e-06
1.765493e-06
1.742932e-06
1.720661e-06
1.698675e-06
1.676971e-06
1.655545e-06
1.634394e-06
1.613515e-06
1.592903e-06
1.572555e-06
1.552468e-06
1.532639e-06
1.513064e-06
1.493740e-06
1.474663e-06
1.455831e-06
1.437241e-06
1.418888e-06
1.400771e-06
1.382886e-06
1.365230e-06
1.347800e-06
1.330594e-06
1.313608e-06
</radial_function>
</projector>
<projector l="1" size="1178">
<radial_potential>
5.225098
5.223427
5.218416
5.210067
5.198387
5.183382
5.165065
5.143446
5.118540
5.090365
5.058939
5.024284
4.986424
4.945384
4.901192
4.853880
4.803479
4.750024
4.693554
4.634106
4.571723
4.506449
4.438329
4.367413
4.293750
4.217395
4.138401
4.056827
3.972732
3.886178
3.797229
3.705952
3.612415
3.516690
3.418848
3.318967
3.217124
3.113398
3.007871
2.900629
2.791758
2.681347
2.569487
2.456271
2.341795
2.226158
2.109459
1.991801
1.873289
1.754029
1.634131
1.513706
1.392868
1.271733
1.150420
1.029048
0.907740
0.786622
0.665820
0.545465
0.425687
0.306622
0.188404
0.071173
-0.044930
-0.159763
-0.273181
-0.385035
-0.495177
-0.603454
-0.709711
-0.813820
-0.915758
-1.015530
-1.113144
-1.208609
-1.301933
-1.393129
-1.482207
-1.569181
-1.654064
-1.736872
-1.817618
-1.896320
-1.972995
-2.047659
-2.120331
-2.191030
-2.259775
-2.326585
-2.391481
-2.454484
-2.515615
-2.574896
-2.632350
-2.687998
-2.741865
-2.793974
-2.844349
-2.893015
-2.939997
-2.985322
-3.029014
-3.071100
-3.111609
-3.150567
-3.188002
-3.223944
-3.258422
-3.291465
-3.323104
-3.353369
-3.382293
-3.409907
-3.436243
-3.461336
-3.485220
-3.507927
-3.529495
-3.549958
-3.569353
-3.587717
-3.605087
-3.621502
-3.637001
-3.651624
-3.665411
-3.678402
-3.690640
-3.702166
-3.713024
-3.723257
-3.732910
-3.742028
-3.750655
-3.758839
-3.766626
-3.774063
-3.781200
-3.788084
-3.794765
-3.801280
-3.807617
-3.813748
-3.819652
-3.825304
-3.830684
-3.835771
-3.840545
-3.844989
-3.849086
-3.852819
-3.856176
-3.859141
-3.861705
-3.863854
-3.865579
-3.866872
-3.867727
-3.868142
-3.868113
-3.867633
-3.866689
-3.865282
-3.863411
-3.861075
-3.858273
-3.855007
-3.851280
-3.847093
-3.842450
-3.837356
-3.831815
-3.825834
-3.819418
-3.812574
-3.805311
-3.797635
-3.789555
-3.781081
-3.772222
-3.762987
-3.753387
-3.743432
-3.733133
-3.722502
-3.711550
-3.700288
-3.688728
-3.676882
-3.664762
-3.652381
-3.639750
-3.626882
-3.613789
-3.600484
-3.586978
-3.573285
-3.559415
-3.545382
-3.531197
-3.516872
-3.502418
-3.487848
-3.473172
-3.458401
-3.443547
-3.428619
-3.413629
-3.398586
-3.383500
-3.368382
-3.353239
-3.338082
-3.322918
-3.307757
-3.292606
-3.277473
-3.262365
-3.247290
-3.232255
-3.217266
-3.202329
-3.187450
-3.172635
-3.157888
-3.143215
-3.128621
-3.114109
-3.099683
-3.085348
-3.071107
-3.056963
-3.042919
-3.028977
-3.015140
-3.001410
-2.987788
-2.974278
-2.960879
-2.947593
-2.934421
-2.921363
-2.908422
-2.895596
-2.882886
-2.870293
-2.857816
-2.845454
-2.833209
-2.821078
-2.809063
-2.797161
-2.785372
-2.773695
-2.762130
-2.750676
-2.739330
-2.728092
-2.716962
-2.705936
-2.695015
-2.684197
-2.673481
-2.662864
-2.652347
-2.641926
-2.631601
-2.621371
-2.611233
-2.601187
-2.591231
-2.581363
-2.571582
-2.561887
-2.552276
-2.542748
-2.533302
-2.523935
-2.514648
-2.505437
-2.496303
-2.487244
-2.478258
-2.469345
-2.460504
-2.451732
-2.443029
-2.434395
-2.425827
-2.417325
-2.408887
-2.400514
-2.392203
-2.383954
-2.375766
-2.367639
-2.359570
-2.351560
-2.343608
-2.335712
-2.327872
-2.320088
-2.312358
-2.304682
-2.297059
-2.289489
-2.281970
-2.274503
-2.267086
-2.259719
-2.252402
-2.245133
-2.237912
-2.230740
-2.223614
-2.216535
-2.209502
-2.202515
-2.195573
-2.188675
-2.181822
-2.175012
-2.168245
-2.161522
-2.154840
-2.148201
-2.141603
-2.135046
-2.128530
-2.122054
-2.115618
-2.109222
-2.102864
-2.096546
-2.090266
-2.084023
-2.077819
-2.071652
-2.065521
-2.059428
-2.053370
-2.047349
-2.041363
-2.035412
-2.029496
-2.023615
-2.017768
-2.011956
-2.006177
-2.000431
-1.994719
-1.989039
-1.983392
-1.977777
-1.972194
-1.966643
-1.961123
-1.955634
-1.950177
-1.944749
-1.939353
-1.933986
-1.928649
-1.923341
-1.918063
-1.912814
-1.907594
-1.902403
-1.897240
-1.892104
-1.886997
-1.881918
-1.876866
-1.871841
-1.866843
-1.861872
-1.856927
-1.852009
-1.847117
-1.842250
-1.837410
-1.832595
-1.827805
-1.823040
-1.818300
-1.813585
-1.808894
-1.804228
-1.799586
-1.794967
-1.790373
-1.785802
-1.781254
-1.776730
-1.772228
-1.767749
-1.763293
-1.758860
-1.754449
-1.750060
-1.745692
-1.741347
-1.737024
-1.732721
-1.728441
-1.724181
-1.719942
-1.715724
-1.711527
-1.707350
-1.703194
-1.699058
-1.694942
-1.690846
-1.686770
-1.682714
-1.678677
-1.674659
-1.670661
-1.666681
-1.662721
-1.658779
-1.654856
-1.650952
-1.647066
-1.643198
-1.639349
-1.635517
-1.631704
-1.627908
-1.624130
-1.620369
-1.616626
-1.612900
-1.609191
-1.605500
-1.601825
-1.598167
-1.594525
-1.590901
-1.587292
-1.583700
-1.580125
-1.576565
-1.573022
-1.569494
-1.565982
-1.562486
-1.559005
-1.555540
-1.552091
-1.548656
-1.545237
-1.541833
-1.538444
-1.535070
-1.531710
-1.528365
-1.525035
-1.521720
-1.518418
-1.515131
-1.511858
-1.508600
-1.505355
-1.502124
-1.498908
-1.495704
-1.492515
-1.489339
-1.486177
-1.483028
-1.479892
-1.476770
-1.473661
-1.470565
-1.467481
-1.464411
-1.461354
-1.458309
-1.455277
-1.452258
-1.449251
-1.446256
-1.443274
-1.440304
-1.437347
-1.434401
-1.431468
-1.428546
-1.425637
-1.422739
-1.419853
-1.416979
-1.414116
-1.411265
-1.408425
-1.405597
-1.402780
-1.399975
-1.397180
-1.394397
-1.391625
-1.388863
-1.386113
-1.383374
-1.380645
-1.377927
-1.375220
-1.372524
-1.369838
-1.367162
-1.364497
-1.361842
-1.359198
-1.356564
-1.353940
-1.351326
-1.348723
-1.346129
-1.343545
-1.340971
-1.338407
-1.335853
-1.333309
-1.330774
-1.328249
-1.325733
-1.323227
-1.320730
-1.318243
-1.315765
-1.313297
-1.310837
-1.308387
-1.305946
-1.303514
-1.301092
-1.298678
-1.296273
-1.293877
-1.291490
-1.289111
-1.286741
-1.284381
-1.282028
-1.279685
-1.277349
-1.275023
-1.272705
-1.270395
-1.268093
-1.265800
-1.263516
-1.261239
-1.258971
-1.256710
-1.254458
-1.252214
-1.249978
-1.247750
-1.245530
-1.243318
-1.241113
-1.238917
-1.236728
-1.234547
-1.232373
-1.230207
-1.228049
-1.225899
-1.223756
-1.221620
-1.219492
-1.217371
-1.215257
-1.213151
-1.211053
-1.208961
-1.206877
-1.204799
-1.202729
-1.200666
-1.198611
-1.196562
-1.194520
-1.192485
-1.190457
-1.188436
-1.186422
-1.184414
-1.182414
-1.180420
-1.178432
-1.176452
-1.174478
-1.172511
-1.170550
-1.168596
-1.166648
-1.164707
-1.162773
-1.160844
-1.158923
-1.157007
-1.155098
-1.153195
-1.151298
-1.149408
-1.147524
-1.145646
-1.143774
-1.141908
-1.140048
-1.138194
-1.136347
-1.134505
-1.132669
-1.130840
-1.129016
-1.127198
-1.125386
-1.123579
-1.121779
-1.119984
-1.118195
-1.116412
-1.114634
-1.112862
-1.111095
-1.109335
-1.107579
-1.105830
-1.104086
-1.102347
-1.100614
-1.098886
-1.097164
-1.095447
-1.093735
-1.092029
-1.090328
-1.088632
-1.086942
-1.085257
-1.083577
-1.081902
-1.080233
-1.078568
-1.076909
-1.075255
-1.073606
-1.071962
-1.070323
-1.068688
-1.067059
-1.065435
-1.063816
-1.062202
-1.060593
-1.058988
-1.057388
-1.055794
-1.054204
-1.052618
-1.051038
-1.049462
-1.047891
-1.046325
-1.044763
-1.043206
-1.041654
-1.040106
-1.038563
-1.037025
-1.035491
-1.033961
-1.032436
-1.030916
-1.029400
-1.027888
-1.026381
-1.024878
-1.023380
-1.021886
-1.020396
-1.018911
-1.017430
-1.015954
-1.014481
-1.013013
-1.011549
-1.010090
-1.008634
-1.007183
-1.005736
-1.004293
-1.002854
-1.001420
-0.999989
-0.998563
-0.997140
-0.995722
-0.994307
-0.992897
-0.991491
-0.990088
-0.988690
-0.987296
-0.985905
-0.984518
-0.983136
-0.981757
-0.980382
-0.979011
-0.977643
-0.976280
-0.974920
-0.973564
-0.972212
-0.970864
-0.969519
-0.968178
-0.966841
-0.965508
-0.964178
-0.962851
-0.961529
-0.960210
-0.958895
-0.957583
-0.956275
-0.954970
-0.953669
-0.952372
-0.951078
-0.949787
-0.948500
-0.947217
-0.945937
-0.944660
-0.943387
-0.942118
-0.940851
-0.939589
-0.938329
-0.937073
-0.935820
-0.934571
-0.933325
-0.932082
-0.930843
-0.929606
-0.928374
-0.927144
-0.925918
-0.924695
-0.923475
-0.922258
-0.921045
-0.919834
-0.918627
-0.917423
-0.916222
-0.915025
-0.913830
-0.912639
-0.911451
-0.910265
-0.909083
-0.907904
-0.906728
-0.905555
-0.904385
-0.903218
-0.902054
-0.900893
-0.899736
-0.898581
-0.897429
-0.896280
-0.895133
-0.893990
-0.892850
-0.891713
-0.890578
-0.889447
-0.888318
-0.887192
-0.886069
-0.884949
-0.883831
-0.882717
-0.881605
-0.880496
-0.879390
-0.878287
-0.877186
-0.876088
-0.874993
-0.873901
-0.872811
-0.871724
-0.870640
-0.869559
-0.868480
-0.867404
-0.866330
-0.865259
-0.864191
-0.863126
-0.862063
-0.861002
-0.859945
-0.858890
-0.857837
-0.856787
-0.855740
-0.854695
-0.853653
-0.852613
-0.851576
-0.850541
-0.849509
-0.848479
-0.847452
-0.846427
-0.845405
-0.844385
-0.843368
-0.842353
-0.841341
-0.840331
-0.839323
-0.838318
-0.837315
-0.836315
-0.835317
-0.834321
-0.833328
-0.832337
-0.831349
-0.830362
-0.829379
-0.828397
-0.827418
-0.826441
-0.825466
-0.824494
-0.823524
-0.822557
-0.821591
-0.820628
-0.819667
-0.818708
-0.817752
-0.816798
-0.815846
-0.814896
-0.813949
-0.813003
-0.812060
-0.811119
-0.810180
-0.809244
-0.808309
-0.807377
-0.806447
-0.805519
-0.804593
-0.803669
-0.802748
-0.801828
-0.800911
-0.799995
-0.799082
-0.798171
-0.797262
-0.796355
-0.795450
-0.794547
-0.793646
-0.792748
-0.791851
-0.790956
-0.790063
-0.789173
-0.788284
-0.787397
-0.786513
-0.785630
-0.784749
-0.783870
-0.782994
-0.782119
-0.781246
-0.780375
-0.779506
-0.778639
-0.777774
-0.776911
-0.776049
-0.775190
-0.774332
-0.773477
-0.772623
-0.771771
-0.770921
-0.770073
-0.769227
-0.768383
-0.767540
-0.766699
-0.765861
-0.765024
-0.764188
-0.763355
-0.762524
-0.761694
-0.760866
-0.760040
-0.759215
-0.758393
-0.757572
-0.756753
-0.755936
-0.755121
-0.754307
-0.753495
-0.752685
-0.751876
-0.751070
-0.750265
-0.749461
-0.748660
-0.747860
-0.747062
-0.746265
-0.745471
-0.744678
-0.743886
-0.743097
-0.742309
-0.741522
-0.740738
-0.739955
-0.739173
-0.738393
-0.737615
-0.736839
-0.736064
-0.735291
-0.734519
-0.733750
-0.732981
-0.732215
-0.731449
-0.730686
-0.729924
-0.729164
-0.728405
-0.727648
-0.726892
-0.726138
-0.725386
-0.724635
-0.723885
-0.723138
-0.722391
-0.721647
-0.720903
-0.720162
-0.719422
-0.718683
-0.717946
-0.717210
-0.716476
-0.715744
-0.715013
-0.714283
-0.713555
-0.712828
-0.712103
-0.711379
-0.710657
-0.709937
-0.709217
-0.708499
-0.707783
-0.707068
-0.706355
-0.705643
-0.704932
-0.704223
-0.703515
-0.702809
-0.702104
-0.701400
-0.700698
-0.699998
-0.699298
-0.698600
-0.697904
-0.697209
-0.696515
-0.695823
-0.695132
-0.694442
-0.693754
-0.693067
-0.692381
-0.691697
-0.691014
-0.690333
-0.689653
-0.688974
-0.688297
-0.687621
-0.686946
-0.686272
-0.685600
-0.684929
-0.684260
-0.683592
-0.682925
-0.682259
-0.681595
-0.680932
-0.680270
-0.679610
-0.678950
-0.678292
-0.677636
-0.676981
-0.676326
-0.675674
-0.675022
-0.674372
-0.673723
-0.673075
-0.672428
-0.671783
-0.671139
-0.670496
-0.669855
-0.669214
-0.668575
-0.667937
-0.667300
-0.666665
-0.666030
-0.665397
-0.664765
-0.664135
-0.663505
-0.662877
-0.662250
-0.661624
-0.660999
-0.660376
-0.659753
-0.659132
-0.658512
-0.657893
-0.657275
-0.656659
-0.656043
-0.655429
-0.654816
-0.654204
-0.653593
-0.652983
-0.652375
-0.651767
-0.651161
-0.650556
-0.649952
-0.649349
-0.648747
-0.648147
-0.647547
-0.646948
-0.646351
-0.645755
-0.645160
-0.644566
-0.643973
-0.643381
-0.642790
-0.642200
-0.641612
-0.641024
-0.640438
-0.639852
-0.639268
-0.638685
-0.638102
-0.637521
-0.636941
-0.636362
-0.635784
-0.635207
-0.634631
-0.634057
-0.633483
-0.632910
-0.632338
-0.631768
-0.631198
-0.630629
-0.630062
-0.629495
-0.628929
-0.628365
-0.627801
-0.627239
-0.626677
-0.626117
-0.625557
-0.624999
-0.624441
-0.623885
-0.623329
-0.622774
-0.622221
-0.621668
-0.621117
-0.620566
-0.620016
-0.619468
-0.618920
-0.618373
-0.617828
-0.617283
-0.616739
-0.616196
-0.615654
-0.615113
-0.614573
-0.614034
-0.613496
-0.612959
-0.612422
-0.611887
-0.611353
-0.610819
-0.610287
-0.609755
-0.609224
-0.608695
-0.608166
-0.607638
-0.607111
-0.606585
-0.606059
-0.605535
-0.605012
-0.604489
-0.603968
-0.603447
-0.602927
-0.602409
-0.601891
-0.601374
-0.600857
-0.600342
-0.599828
-0.599314
-0.598801
-0.598290
-0.597779
-0.597269
-0.596759
-0.596251
-0.595744
-0.595237
-0.594731
</radial_potential>
<radial_function>
0.000000e+00
9.510874e-04
1.903467e-03
2.858416e-03
3.817211e-03
4.781130e-03
5.751442e-03
6.729414e-03
7.716303e-03
8.713360e-03
9.721825e-03
1.074293e-02
1.177789e-02
1.282791e-02
1.389418e-02
1.497787e-02
1.608015e-02
1.720216e-02
1.834502e-02
1.950982e-02
2.069765e-02
2.190957e-02
2.314662e-02
2.440979e-02
2.570007e-02
2.701842e-02
2.836577e-02
2.974302e-02
3.115102e-02
3.259063e-02
3.406263e-02
3.556781e-02
3.710688e-02
3.868056e-02
4.028951e-02
4.193434e-02
4.361564e-02
4.533396e-02
4.708979e-02
4.888361e-02
5.071583e-02
5.258682e-02
5.449693e-02
5.644643e-02
5.843556e-02
6.046454e-02
6.253349e-02
6.464252e-02
6.679170e-02
6.898102e-02
7.121043e-02
7.347986e-02
7.578915e-02
7.813811e-02
8.052652e-02
8.295407e-02
8.542043e-02
8.792521e-02
9.046797e-02
9.304822e-02
9.566544e-02
9.831903e-02
1.010084e-01
1.037328e-01
1.064915e-01
1.092838e-01
1.121089e-01
1.149659e-01
1.178538e-01
1.207718e-01
1.237188e-01
1.266939e-01
1.296959e-01
1.327237e-01
1.357763e-01
1.388524e-01
1.419508e-01
1.450703e-01
1.482096e-01
1.513674e-01
1.545424e-01
1.577332e-01
1.609384e-01
1.641567e-01
1.673867e-01
1.706268e-01
1.738758e-01
1.771320e-01
1.803940e-01
1.836604e-01
1.869296e-01
1.902002e-01
1.934707e-01
1.967395e-01
2.000052e-01
2.032663e-01
2.065213e-01
2.097686e-01
2.130070e-01
2.162348e-01
2.194506e-01
2.226530e-01
2.258407e-01
2.290121e-01
2.321659e-01
2.353008e-01
2.384154e-01
2.415084e-01
2.445786e-01
2.476246e-01
2.506453e-01
2.536395e-01
2.566060e-01
2.595436e-01
2.624512e-01
2.653279e-01
2.681725e-01
2.709840e-01
2.737615e-01
2.765040e-01
2.792106e-01
2.818805e-01
2.845129e-01
2.871068e-01
2.896615e-01
2.921764e-01
2.946507e-01
2.970836e-01
2.994746e-01
3.018231e-01
3.041284e-01
3.063900e-01
3.086073e-01
3.107798e-01
3.129071e-01
3.149885e-01
3.170237e-01
3.190122e-01
3.209536e-01
3.228474e-01
3.246932e-01
3.264906e-01
3.282392e-01
3.299386e-01
3.315883e-01
3.331880e-01
3.347373e-01
3.362359e-01
3.376833e-01
3.390793e-01
3.404235e-01
3.417157e-01
3.429556e-01
3.441429e-01
3.452774e-01
3.463589e-01
3.473872e-01
3.483623e-01
3.492840e-01
3.501522e-01
3.509669e-01
3.517280e-01
3.524356e-01
3.530898e-01
3.536905e-01
3.542379e-01
3.547322e-01
3.551735e-01
3.555621e-01
3.558982e-01
3.561820e-01
3.564139e-01
3.565942e-01
3.567233e-01
3.568016e-01
3.568295e-01
3.568075e-01
3.567361e-01
3.566157e-01
3.564470e-01
3.562305e-01
3.559669e-01
3.556566e-01
3.553004e-01
3.548989e-01
3.544529e-01
3.539630e-01
3.534299e-01
3.528544e-01
3.522373e-01
3.515792e-01
3.508811e-01
3.501437e-01
3.493679e-01
3.485543e-01
3.477040e-01
3.468176e-01
3.458961e-01
3.449404e-01
3.439512e-01
3.429294e-01
3.418759e-01
3.407916e-01
3.396772e-01
3.385338e-01
3.373621e-01
3.361630e-01
3.349374e-01
3.336861e-01
3.324099e-01
3.311098e-01
3.297865e-01
3.284409e-01
3.270737e-01
3.256859e-01
3.242781e-01
3.228513e-01
3.214062e-01
3.199435e-01
3.184640e-01
3.169685e-01
3.154576e-01
3.139322e-01
3.123930e-01
3.108406e-01
3.092757e-01
3.076990e-01
3.061112e-01
3.045129e-01
3.029048e-01
3.012874e-01
2.996614e-01
2.980273e-01
2.963858e-01
2.947373e-01
2.930825e-01
2.914219e-01
2.897561e-01
2.880854e-01
2.864104e-01
2.847316e-01
2.830495e-01
2.813645e-01
2.796770e-01
2.779875e-01
2.762964e-01
2.746041e-01
2.729110e-01
2.712175e-01
2.695238e-01
2.678305e-01
2.661378e-01
2.644461e-01
2.627556e-01
2.610667e-01
2.593797e-01
2.576949e-01
2.560126e-01
2.543329e-01
2.526563e-01
2.509829e-01
2.493130e-01
2.476467e-01
2.459844e-01
2.443263e-01
2.426725e-01
2.410233e-01
2.393788e-01
2.377392e-01
2.361047e-01
2.344755e-01
2.328517e-01
2.312335e-01
2.296210e-01
2.280145e-01
2.264139e-01
2.248194e-01
2.232313e-01
2.216495e-01
2.200742e-01
2.185056e-01
2.169436e-01
2.153885e-01
2.138402e-01
2.122989e-01
2.107648e-01
2.092377e-01
2.077179e-01
2.062055e-01
2.047003e-01
2.032027e-01
2.017125e-01
2.002298e-01
1.987548e-01
1.972874e-01
1.958277e-01
1.943758e-01
1.929317e-01
1.914954e-01
1.900669e-01
1.886463e-01
1.872337e-01
1.858290e-01
1.844322e-01
1.830435e-01
1.816628e-01
1.802901e-01
1.789254e-01
1.775688e-01
1.762203e-01
1.748799e-01
1.735475e-01
1.722232e-01
1.709071e-01
1.695990e-01
1.682990e-01
1.670071e-01
1.657233e-01
1.644476e-01
1.631800e-01
1.619204e-01
1.606689e-01
1.594255e-01
1.581901e-01
1.569627e-01
1.557434e-01
1.545320e-01
1.533286e-01
1.521333e-01
1.509458e-01
1.497663e-01
1.485947e-01
1.474310e-01
1.462751e-01
1.451271e-01
1.439869e-01
1.428545e-01
1.417299e-01
1.406130e-01
1.395039e-01
1.384024e-01
1.373086e-01
1.362225e-01
1.351439e-01
1.340729e-01
1.330095e-01
1.319536e-01
1.309052e-01
1.298642e-01
1.288307e-01
1.278045e-01
1.267857e-01
1.257742e-01
1.247700e-01
1.237731e-01
1.227833e-01
1.218008e-01
1.208254e-01
1.198572e-01
1.188960e-01
1.179418e-01
1.169947e-01
1.160545e-01
1.151213e-01
1.141950e-01
1.132755e-01
1.123629e-01
1.114570e-01
1.105579e-01
1.096655e-01
1.087798e-01
1.079007e-01
1.070283e-01
1.061623e-01
1.053029e-01
1.044500e-01
1.036036e-01
1.027635e-01
1.019299e-01
1.011025e-01
1.002815e-01
9.946666e-02
9.865809e-02
9.785570e-02
9.705944e-02
9.626930e-02
9.548521e-02
9.470716e-02
9.393509e-02
9.316898e-02
9.240878e-02
9.165445e-02
9.090596e-02
9.016327e-02
8.942635e-02
8.869514e-02
8.796962e-02
8.724976e-02
8.653550e-02
8.582681e-02
8.512366e-02
8.442602e-02
8.373383e-02
8.304707e-02
8.236570e-02
8.168967e-02
8.101897e-02
8.035354e-02
7.969336e-02
7.903838e-02
7.838857e-02
7.774389e-02
7.710431e-02
7.646980e-02
7.584031e-02
7.521581e-02
7.459627e-02
7.398165e-02
7.337191e-02
7.276703e-02
7.216697e-02
7.157168e-02
7.098114e-02
7.039532e-02
6.981418e-02
6.923768e-02
6.866579e-02
6.809849e-02
6.753573e-02
6.697748e-02
6.642370e-02
6.587438e-02
6.532947e-02
6.478894e-02
6.425276e-02
6.372089e-02
6.319331e-02
6.266998e-02
6.215088e-02
6.163596e-02
6.112520e-02
6.061857e-02
6.011603e-02
5.961756e-02
5.912313e-02
5.863270e-02
5.814624e-02
5.766373e-02
5.718514e-02
5.671042e-02
5.623957e-02
5.577254e-02
5.530931e-02
5.484984e-02
5.439411e-02
5.394210e-02
5.349377e-02
5.304909e-02
5.260803e-02
5.217058e-02
5.173669e-02
5.130635e-02
5.087952e-02
5.045618e-02
5.003631e-02
4.961986e-02
4.920683e-02
4.879718e-02
4.839088e-02
4.798791e-02
4.758824e-02
4.719185e-02
4.679871e-02
4.640880e-02
4.602209e-02
4.563855e-02
4.525817e-02
4.488091e-02
4.450675e-02
4.413567e-02
4.376765e-02
4.340265e-02
4.304065e-02
4.268164e-02
4.232559e-02
4.197247e-02
4.162226e-02
4.127494e-02
4.093048e-02
4.058887e-02
4.025007e-02
3.991408e-02
3.958085e-02
3.925038e-02
3.892265e-02
3.859762e-02
3.827527e-02
3.795560e-02
3.763857e-02
3.732416e-02
3.701235e-02
3.670313e-02
3.639647e-02
3.609235e-02
3.579074e-02
3.549164e-02
3.519502e-02
3.490086e-02
3.460913e-02
3.431983e-02
3.403293e-02
3.374840e-02
3.346625e-02
3.318643e-02
3.290894e-02
3.263375e-02
3.236085e-02
3.209022e-02
3.182183e-02
3.155568e-02
3.129174e-02
3.103000e-02
3.077044e-02
3.051303e-02
3.025777e-02
3.000463e-02
2.975360e-02
2.950466e-02
2.925779e-02
2.901298e-02
2.877021e-02
2.852946e-02
2.829072e-02
2.805397e-02
2.781919e-02
2.758637e-02
2.735550e-02
2.712654e-02
2.689950e-02
2.667436e-02
2.645109e-02
2.622968e-02
2.601013e-02
2.579240e-02
2.557650e-02
2.536239e-02
2.515008e-02
2.493954e-02
2.473076e-02
2.452372e-02
2.431842e-02
2.411483e-02
2.391294e-02
2.371274e-02
2.351421e-02
2.331734e-02
2.312212e-02
2.292854e-02
2.273657e-02
2.254621e-02
2.235744e-02
2.217025e-02
2.198463e-02
2.180056e-02
2.161803e-02
2.143703e-02
2.125755e-02
2.107957e-02
2.090307e-02
2.072806e-02
2.055452e-02
2.038242e-02
2.021177e-02
2.004255e-02
1.987474e-02
1.970835e-02
1.954334e-02
1.937972e-02
1.921747e-02
1.905659e-02
1.889705e-02
1.873884e-02
1.858197e-02
1.842641e-02
1.827215e-02
1.811919e-02
1.796751e-02
1.781710e-02
1.766796e-02
1.752006e-02
1.737341e-02
1.722798e-02
1.708378e-02
1.694079e-02
1.679899e-02
1.665839e-02
1.651897e-02
1.638071e-02
1.624362e-02
1.610768e-02
1.597288e-02
1.583921e-02
1.570666e-02
1.557522e-02
1.544489e-02
1.531566e-02
1.518750e-02
1.506043e-02
1.493442e-02
1.480947e-02
1.468557e-02
1.456271e-02
1.444088e-02
1.432007e-02
1.420028e-02
1.408150e-02
1.396371e-02
1.384691e-02
1.373110e-02
1.361625e-02
1.350238e-02
1.338945e-02
1.327748e-02
1.316645e-02
1.305635e-02
1.294717e-02
1.283892e-02
1.273157e-02
1.262512e-02
1.251957e-02
1.241491e-02
1.231112e-02
1.220821e-02
1.210616e-02
1.200497e-02
1.190463e-02
1.180513e-02
1.170647e-02
1.160864e-02
1.151163e-02
1.141544e-02
1.132005e-02
1.122546e-02
1.113168e-02
1.103867e-02
1.094645e-02
1.085501e-02
1.076433e-02
1.067442e-02
1.058526e-02
1.049685e-02
1.040919e-02
1.032226e-02
1.023606e-02
1.015058e-02
1.006583e-02
9.981785e-03
9.898448e-03
9.815811e-03
9.733868e-03
9.652615e-03
9.572044e-03
9.492150e-03
9.412928e-03
9.334371e-03
9.256474e-03
9.179233e-03
9.102640e-03
9.026691e-03
8.951380e-03
8.876702e-03
8.802651e-03
8.729223e-03
8.656411e-03
8.584212e-03
8.512619e-03
8.441627e-03
8.371232e-03
8.301429e-03
8.232212e-03
8.163576e-03
8.095517e-03
8.028030e-03
7.961110e-03
7.894752e-03
7.828952e-03
7.763704e-03
7.699004e-03
7.634848e-03
7.571230e-03
7.508147e-03
7.445594e-03
7.383566e-03
7.322060e-03
7.261069e-03
7.200591e-03
7.140621e-03
7.081154e-03
7.022187e-03
6.963715e-03
6.905734e-03
6.848240e-03
6.791228e-03
6.734695e-03
6.678637e-03
6.623049e-03
6.567928e-03
6.513270e-03
6.459070e-03
6.405326e-03
6.352032e-03
6.299186e-03
6.246784e-03
6.194821e-03
6.143294e-03
6.092200e-03
6.041534e-03
5.991294e-03
5.941475e-03
5.892074e-03
5.843088e-03
5.794512e-03
5.746344e-03
5.698581e-03
5.651218e-03
5.604252e-03
5.557680e-03
5.511498e-03
5.465704e-03
5.420294e-03
5.375265e-03
5.330614e-03
5.286337e-03
5.242431e-03
5.198893e-03
5.155720e-03
5.112909e-03
5.070458e-03
5.028362e-03
4.986618e-03
4.945225e-03
4.904179e-03
4.863476e-03
4.823115e-03
4.783092e-03
4.743404e-03
4.704049e-03
4.665023e-03
4.626325e-03
4.587951e-03
4.549898e-03
4.512164e-03
4.474746e-03
4.437641e-03
4.400847e-03
4.364361e-03
4.328181e-03
4.292304e-03
4.256727e-03
4.221448e-03
4.186464e-03
4.151773e-03
4.117373e-03
4.083261e-03
4.049434e-03
4.015890e-03
3.982627e-03
3.949642e-03
3.916933e-03
3.884498e-03
3.852334e-03
3.820439e-03
3.788812e-03
3.757448e-03
3.726347e-03
3.695506e-03
3.664924e-03
3.634596e-03
3.604523e-03
3.574701e-03
3.545128e-03
3.515802e-03
3.486722e-03
3.457885e-03
3.429288e-03
3.400931e-03
3.372811e-03
3.344926e-03
3.317273e-03
3.289852e-03
3.262660e-03
3.235695e-03
3.208955e-03
3.182439e-03
3.156144e-03
3.130069e-03
3.104211e-03
3.078570e-03
3.053142e-03
3.027927e-03
3.002923e-03
2.978127e-03
2.953538e-03
2.929154e-03
2.904974e-03
2.880996e-03
2.857217e-03
2.833638e-03
2.810254e-03
2.787066e-03
2.764072e-03
2.741269e-03
2.718656e-03
2.696232e-03
2.673996e-03
2.651944e-03
2.630076e-03
2.608391e-03
2.586886e-03
2.565561e-03
2.544414e-03
2.523442e-03
2.502646e-03
2.482023e-03
2.461572e-03
2.441291e-03
2.421179e-03
2.401234e-03
2.381456e-03
2.361843e-03
2.342393e-03
2.323104e-03
2.303977e-03
2.285009e-03
2.266198e-03
2.247545e-03
2.229046e-03
2.210702e-03
2.192510e-03
2.174470e-03
2.156580e-03
2.138838e-03
2.121245e-03
2.103797e-03
2.086495e-03
2.069337e-03
2.052321e-03
2.035447e-03
2.018714e-03
2.002119e-03
1.985662e-03
1.969343e-03
1.953159e-03
1.937109e-03
1.921193e-03
1.905409e-03
1.889756e-03
1.874234e-03
1.858840e-03
1.843574e-03
1.828435e-03
1.813422e-03
1.798534e-03
1.783769e-03
1.769127e-03
1.754606e-03
1.740206e-03
1.725926e-03
1.711764e-03
1.697719e-03
1.683792e-03
1.669979e-03
1.656282e-03
1.642698e-03
1.629227e-03
1.615867e-03
1.602619e-03
1.589480e-03
1.576450e-03
1.563528e-03
1.550714e-03
1.538006e-03
1.525403e-03
1.512904e-03
1.500509e-03
1.488217e-03
1.476027e-03
1.463938e-03
1.451949e-03
1.440059e-03
1.428268e-03
1.416575e-03
1.404978e-03
1.393477e-03
1.382072e-03
1.370761e-03
1.359544e-03
1.348420e-03
1.337387e-03
1.326446e-03
1.315596e-03
1.304835e-03
1.294164e-03
1.283581e-03
1.273085e-03
1.262676e-03
1.252354e-03
1.242116e-03
1.231964e-03
1.221895e-03
1.211910e-03
1.202007e-03
1.192186e-03
1.182446e-03
1.172787e-03
1.163207e-03
1.153707e-03
1.144286e-03
1.134942e-03
1.125675e-03
1.116485e-03
1.107371e-03
1.098332e-03
1.089367e-03
1.080477e-03
1.071660e-03
1.062916e-03
1.054245e-03
1.045644e-03
1.037115e-03
1.028656e-03
1.020267e-03
1.011947e-03
1.003696e-03
9.955132e-04
9.873976e-04
9.793490e-04
9.713667e-04
9.634503e-04
9.555992e-04
9.478128e-04
9.400906e-04
9.324320e-04
9.248366e-04
9.173038e-04
9.098331e-04
9.024240e-04
8.950759e-04
8.877883e-04
8.805608e-04
8.733928e-04
8.662839e-04
8.592335e-04
8.522412e-04
8.453064e-04
8.384288e-04
8.316078e-04
8.248429e-04
8.181337e-04
8.114797e-04
8.048805e-04
7.983356e-04
7.918445e-04
7.854069e-04
7.790222e-04
7.726900e-04
7.664099e-04
7.601815e-04
7.540042e-04
7.478778e-04
7.418017e-04
7.357756e-04
7.297990e-04
7.238715e-04
7.179928e-04
7.121623e-04
7.063798e-04
7.006447e-04
6.949568e-04
6.893156e-04
6.837208e-04
6.781718e-04
6.726685e-04
6.672103e-04
6.617970e-04
6.564281e-04
6.511032e-04
6.458221e-04
6.405843e-04
6.353895e-04
6.302373e-04
6.251274e-04
6.200594e-04
6.150329e-04
6.100477e-04
6.051034e-04
6.001996e-04
5.953361e-04
5.905124e-04
5.857283e-04
5.809833e-04
5.762773e-04
5.716098e-04
5.669806e-04
5.623893e-04
5.578356e-04
5.533193e-04
5.488399e-04
5.443972e-04
5.399909e-04
5.356207e-04
5.312863e-04
5.269873e-04
5.227236e-04
5.184947e-04
5.143005e-04
5.101406e-04
5.060147e-04
5.019226e-04
4.978639e-04
4.938385e-04
4.898460e-04
4.858862e-04
4.819587e-04
4.780633e-04
4.741999e-04
4.703679e-04
4.665674e-04
4.627979e-04
4.590591e-04
4.553510e-04
4.516732e-04
4.480254e-04
4.444074e-04
4.408189e-04
4.372598e-04
4.337298e-04
4.302285e-04
4.267559e-04
4.233116e-04
4.198955e-04
4.165072e-04
4.131466e-04
4.098134e-04
4.065074e-04
4.032284e-04
3.999762e-04
3.967505e-04
3.935511e-04
3.903778e-04
3.872304e-04
3.841087e-04
3.810124e-04
3.779413e-04
3.748953e-04
3.718742e-04
3.688776e-04
3.659055e-04
3.629576e-04
3.600337e-04
3.571337e-04
3.542573e-04
3.514043e-04
3.485745e-04
3.457678e-04
3.429840e-04
3.402228e-04
3.374841e-04
3.347678e-04
3.320735e-04
3.294011e-04
3.267506e-04
3.241215e-04
3.215139e-04
3.189275e-04
3.163621e-04
3.138177e-04
3.112939e-04
3.087906e-04
3.063077e-04
3.038450e-04
3.014023e-04
2.989795e-04
2.965763e-04
2.941927e-04
2.918285e-04
2.894835e-04
2.871576e-04
2.848505e-04
2.825622e-04
2.802925e-04
2.780412e-04
2.758082e-04
2.735934e-04
2.713965e-04
2.692175e-04
2.670561e-04
2.649124e-04
2.627860e-04
2.606768e-04
2.585848e-04
2.565098e-04
2.544516e-04
2.524101e-04
2.503852e-04
2.483767e-04
2.463845e-04
2.444084e-04
2.424484e-04
2.405043e-04
2.385759e-04
2.366632e-04
2.347659e-04
2.328841e-04
2.310175e-04
2.291660e-04
2.273296e-04
2.255080e-04
2.237011e-04
2.219090e-04
2.201313e-04
2.183680e-04
2.166190e-04
2.148842e-04
2.131634e-04
2.114566e-04
2.097635e-04
2.080842e-04
2.064185e-04
2.047662e-04
2.031273e-04
2.015017e-04
1.998893e-04
1.982898e-04
1.967034e-04
1.951297e-04
1.935688e-04
1.920205e-04
1.904847e-04
1.889614e-04
1.874503e-04
1.859515e-04
1.844648e-04
1.829901e-04
1.815273e-04
1.800763e-04
1.786371e-04
1.772095e-04
1.757934e-04
1.743888e-04
1.729955e-04
1.716135e-04
1.702426e-04
1.688828e-04
1.675340e-04
1.661960e-04
1.648689e-04
1.635525e-04
1.622467e-04
1.609514e-04
1.596666e-04
1.583921e-04
1.571280e-04
1.558740e-04
1.546302e-04
1.533964e-04
1.521725e-04
1.509585e-04
1.497543e-04
1.485598e-04
1.473749e-04
1.461996e-04
1.450338e-04
1.438773e-04
1.427302e-04
1.415923e-04
1.404636e-04
1.393440e-04
</radial_function>
</projector>
<projector l="2" size="1178">
<radial_potential>
-4.695746
-4.695721
-4.695646
-4.695521
-4.695347
-4.695122
-4.694847
-4.694521
-4.694145
-4.693718
-4.693240
-4.692710
-4.692129
-4.691496
-4.690810
-4.690071
-4.689279
-4.688433
-4.687533
-4.686578
-4.685567
-4.684501
-4.683377
-4.682197
-4.680958
-4.679660
-4.678303
-4.676886
-4.675407
-4.673867
-4.672263
-4.670596
-4.668864
-4.667066
-4.665202
-4.663270
-4.661269
-4.659198
-4.657056
-4.654842
-4.652554
-4.650192
-4.647754
-4.645238
-4.642645
-4.639971
-4.637216
-4.634379
-4.631457
-4.628450
-4.625356
-4.622173
-4.618901
-4.615536
-4.612078
-4.608525
-4.604876
-4.601128
-4.597280
-4.593330
-4.589276
-4.585117
-4.580850
-4.576473
-4.571986
-4.567385
-4.562669
-4.557836
-4.552883
-4.547809
-4.542611
-4.537287
-4.531836
-4.526255
-4.520541
-4.514692
-4.508707
-4.502582
-4.496316
-4.489905
-4.483348
-4.476643
-4.469785
-4.462774
-4.455606
-4.448280
-4.440791
-4.433139
-4.425321
-4.417336
-4.409181
-4.400856
-4.392358
-4.383686
-4.374840
-4.365817
-4.356618
-4.347240
-4.337684
-4.327949
-4.318034
-4.307939
-4.297664
-4.287210
-4.276575
-4.265762
-4.254769
-4.243599
-4.232251
-4.220727
-4.209028
-4.197155
-4.185110
-4.172896
-4.160513
-4.147964
-4.135251
-4.122377
-4.109345
-4.096157
-4.082816
-4.069327
-4.055692
-4.041915
-4.028000
-4.013952
-3.999774
-3.985471
-3.971048
-3.956510
-3.941862
-3.927110
-3.912258
-3.897314
-3.882282
-3.867170
-3.851983
-3.836729
-3.821414
-3.806045
-3.790631
-3.775177
-3.759693
-3.744185
-3.728663
-3.713135
-3.697610
-3.682095
-3.666601
-3.651137
-3.635712
-3.620336
-3.605018
-3.589770
-3.574600
-3.559520
-3.544541
-3.529673
-3.514927
-3.500314
-3.485847
-3.471537
-3.457395
-3.443433
-3.429664
-3.416101
-3.402755
-3.389639
-3.376767
-3.364151
-3.351805
-3.339737
-3.327938
-3.316394
-3.305094
-3.294025
-3.283176
-3.272535
-3.262092
-3.251838
-3.241762
-3.231855
-3.222110
-3.212517
-3.203069
-3.193759
-3.184579
-3.175522
-3.166583
-3.157754
-3.149031
-3.140406
-3.131876
-3.123434
-3.115077
-3.106798
-3.098595
-3.090462
-3.082395
-3.074391
-3.066446
-3.058556
-3.050718
-3.042928
-3.035184
-3.027483
-3.019821
-3.012196
-3.004605
-2.997045
-2.989516
-2.982013
-2.974535
-2.967079
-2.959645
-2.952229
-2.944830
-2.937446
-2.930075
-2.922717
-2.915368
-2.908029
-2.900697
-2.893372
-2.886051
-2.878734
-2.871419
-2.864107
-2.856794
-2.849482
-2.842168
-2.834852
-2.827533
-2.820211
-2.812885
-2.805554
-2.798217
-2.790875
-2.783527
-2.776172
-2.768810
-2.761441
-2.754065
-2.746681
-2.739289
-2.731889
-2.724481
-2.717066
-2.709642
-2.702211
-2.694771
-2.687325
-2.679870
-2.672409
-2.664941
-2.657466
-2.649984
-2.642497
-2.635004
-2.627506
-2.620003
-2.612496
-2.604985
-2.597471
-2.589954
-2.582435
-2.574915
-2.567393
-2.559871
-2.552349
-2.544828
-2.537309
-2.529792
-2.522278
-2.514768
-2.507261
-2.499760
-2.492265
-2.484776
-2.477294
-2.469820
-2.462355
-2.454899
-2.447453
-2.440019
-2.432595
-2.425184
-2.417786
-2.410401
-2.403031
-2.395676
-2.388337
-2.381014
-2.373708
-2.366420
-2.359150
-2.351899
-2.344668
-2.337457
-2.330267
-2.323099
-2.315952
-2.308828
-2.301727
-2.294649
-2.287596
-2.280567
-2.273563
-2.266585
-2.259633
-2.252707
-2.245807
-2.238935
-2.232090
-2.225274
-2.218485
-2.211725
-2.204993
-2.198291
-2.191618
-2.184975
-2.178361
-2.171778
-2.165224
-2.158701
-2.152209
-2.145748
-2.139317
-2.132917
-2.126549
-2.120212
-2.113906
-2.107631
-2.101388
-2.095176
-2.088996
-2.082847
-2.076730
-2.070644
-2.064590
-2.058567
-2.052576
-2.046616
-2.040687
-2.034790
-2.028923
-2.023088
-2.017284
-2.011511
-2.005768
-2.000057
-1.994375
-1.988725
-1.983104
-1.977514
-1.971954
-1.966424
-1.960923
-1.955452
-1.950011
-1.944598
-1.939215
-1.933861
-1.928536
-1.923239
-1.917971
-1.912730
-1.907518
-1.902334
-1.897178
-1.892049
-1.886947
-1.881872
-1.876825
-1.871804
-1.866810
-1.861842
-1.856901
-1.851985
-1.847095
-1.842231
-1.837393
-1.832580
-1.827791
-1.823028
-1.818290
-1.813576
-1.808886
-1.804221
-1.799579
-1.794962
-1.790368
-1.785797
-1.781250
-1.776726
-1.772225
-1.767747
-1.763291
-1.758858
-1.754447
-1.750058
-1.745691
-1.741346
-1.737022
-1.732720
-1.728440
-1.724180
-1.719942
-1.715724
-1.711527
-1.707350
-1.703194
-1.699058
-1.694942
-1.690846
-1.686770
-1.682714
-1.678677
-1.674659
-1.670660
-1.666681
-1.662721
-1.658779
-1.654856
-1.650952
-1.647066
-1.643198
-1.639349
-1.635517
-1.631704
-1.627908
-1.624130
-1.620369
-1.616626
-1.612900
-1.609191
-1.605500
-1.601825
-1.598167
-1.594525
-1.590901
-1.587292
-1.583700
-1.580125
-1.576565
-1.573022
-1.569494
-1.565982
-1.562486
-1.559005
-1.555540
-1.552091
-1.548656
-1.545237
-1.541833
-1.538444
-1.535070
-1.531710
-1.528365
-1.525035
-1.521720
-1.518418
-1.515131
-1.511858
-1.508600
-1.505355
-1.502124
-1.498908
-1.495704
-1.492515
-1.489339
-1.486177
-1.483028
-1.479892
-1.476770
-1.473661
-1.470565
-1.467481
-1.464411
-1.461354
-1.458309
-1.455277
-1.452258
-1.449251
-1.446256
-1.443274
-1.440304
-1.437347
-1.434401
-1.431468
-1.428546
-1.425637
-1.422739
-1.419853
-1.416979
-1.414116
-1.411265
-1.408425
-1.405597
-1.402780
-1.399975
-1.397180
-1.394397
-1.391625
-1.388863
-1.386113
-1.383374
-1.380645
-1.377927
-1.375220
-1.372524
-1.369838
-1.367162
-1.364497
-1.361842
-1.359198
-1.356564
-1.353940
-1.351326
-1.348723
-1.346129
-1.343545
-1.340971
-1.338407
-1.335853
-1.333309
-1.330774
-1.328249
-1.325733
-1.323227
-1.320730
-1.318243
-1.315765
-1.313297
-1.310837
-1.308387
-1.305946
-1.303514
-1.301092
-1.298678
-1.296273
-1.293877
-1.291490
-1.289111
-1.286741
-1.284381
-1.282028
-1.279685
-1.277349
-1.275023
-1.272705
-1.270395
-1.268093
-1.265800
-1.263516
-1.261239
-1.258971
-1.256710
-1.254458
-1.252214
-1.249978
-1.247750
-1.245530
-1.243318
-1.241113
-1.238917
-1.236728
-1.234547
-1.232373
-1.230207
-1.228049
-1.225899
-1.223756
-1.221620
-1.219492
-1.217371
-1.215257
-1.213151
-1.211053
-1.208961
-1.206877
-1.204799
-1.202729
-1.200666
-1.198611
-1.196562
-1.194520
-1.192485
-1.190457
-1.188436
-1.186422
-1.184414
-1.182414
-1.180420
-1.178432
-1.176452
-1.174478
-1.172511
-1.170550
-1.168596
-1.166648
-1.164707
-1.162773
-1.160844
-1.158923
-1.157007
-1.155098
-1.153195
-1.151298
-1.149408
-1.147524
-1.145646
-1.143774
-1.141908
-1.140048
-1.138194
-1.136347
-1.134505
-1.132669
-1.130840
-1.129016
-1.127198
-1.125386
-1.123579
-1.121779
-1.119984
-1.118195
-1.116412
-1.114634
-1.112862
-1.111095
-1.109335
-1.107579
-1.105830
-1.104086
-1.102347
-1.100614
-1.098886
-1.097164
-1.095447
-1.093735
-1.092029
-1.090328
-1.088632
-1.086942
-1.085257
-1.083577
-1.081902
-1.080233
-1.078568
-1.076909
-1.075255
-1.073606
-1.071962
-1.070323
-1.068688
-1.067059
-1.065435
-1.063816
-1.062202
-1.060593
-1.058988
-1.057388
-1.055794
-1.054204
-1.052618
-1.051038
-1.049462
-1.047891
-1.046325
-1.044763
-1.043206
-1.041654
-1.040106
-1.038563
-1.037025
-1.035491
-1.033961
-1.032436
-1.030916
-1.029400
-1.027888
-1.026381
-1.024878
-1.023380
-1.021886
-1.020396
-1.018911
-1.017430
-1.015954
-1.014481
-1.013013
-1.011549
-1.010090
-1.008634
-1.007183
-1.005736
-1.004293
-1.002854
-1.001420
-0.999989
-0.998563
-0.997140
-0.995722
-0.994307
-0.992897
-0.991491
-0.990088
-0.988690
-0.987296
-0.985905
-0.984518
-0.983136
-0.981757
-0.980382
-0.979011
-0.977643
-0.976280
-0.974920
-0.973564
-0.972212
-0.970864
-0.969519
-0.968178
-0.966841
-0.965508
-0.964178
-0.962851
-0.961529
-0.960210
-0.958895
-0.957583
-0.956275
-0.954970
-0.953669
-0.952372
-0.951078
-0.949787
-0.948500
-0.947217
-0.945937
-0.944660
-0.943387
-0.942118
-0.940851
-0.939589
-0.938329
-0.937073
-0.935820
-0.934571
-0.933325
-0.932082
-0.930843
-0.929606
-0.928374
-0.927144
-0.925918
-0.924695
-0.923475
-0.922258
-0.921045
-0.919834
-0.918627
-0.917423
-0.916222
-0.915025
-0.913830
-0.912639
-0.911451
-0.910265
-0.909083
-0.907904
-0.906728
-0.905555
-0.904385
-0.903218
-0.902054
-0.900893
-0.899736
-0.898581
-0.897429
-0.896280
-0.895133
-0.893990
-0.892850
-0.891713
-0.890578
-0.889447
-0.888318
-0.887192
-0.886069
-0.884949
-0.883831
-0.882717
-0.881605
-0.880496
-0.879390
-0.878287
-0.877186
-0.876088
-0.874993
-0.873901
-0.872811
-0.871724
-0.870640
-0.869559
-0.868480
-0.867404
-0.866330
-0.865259
-0.864191
-0.863126
-0.862063
-0.861002
-0.859945
-0.858890
-0.857837
-0.856787
-0.855740
-0.854695
-0.853653
-0.852613
-0.851576
-0.850541
-0.849509
-0.848479
-0.847452
-0.846427
-0.845405
-0.844385
-0.843368
-0.842353
-0.841341
-0.840331
-0.839323
-0.838318
-0.837315
-0.836315
-0.835317
-0.834321
-0.833328
-0.832337
-0.831349
-0.830362
-0.829379
-0.828397
-0.827418
-0.826441
-0.825466
-0.824494
-0.823524
-0.822557
-0.821591
-0.820628
-0.819667
-0.818708
-0.817752
-0.816798
-0.815846
-0.814896
-0.813949
-0.813003
-0.812060
-0.811119
-0.810180
-0.809244
-0.808309
-0.807377
-0.806447
-0.805519
-0.804593
-0.803669
-0.802748
-0.801828
-0.800911
-0.799995
-0.799082
-0.798171
-0.797262
-0.796355
-0.795450
-0.794547
-0.793646
-0.792748
-0.791851
-0.790956
-0.790063
-0.789173
-0.788284
-0.787397
-0.786513
-0.785630
-0.784749
-0.783870
-0.782994
-0.782119
-0.781246
-0.780375
-0.779506
-0.778639
-0.777774
-0.776911
-0.776049
-0.775190
-0.774332
-0.773477
-0.772623
-0.771771
-0.770921
-0.770073
-0.769227
-0.768383
-0.767540
-0.766699
-0.765861
-0.765024
-0.764188
-0.763355
-0.762524
-0.761694
-0.760866
-0.760040
-0.759215
-0.758393
-0.757572
-0.756753
-0.755936
-0.755121
-0.754307
-0.753495
-0.752685
-0.751876
-0.751070
-0.750265
-0.749461
-0.748660
-0.747860
-0.747062
-0.746265
-0.745471
-0.744678
-0.743886
-0.743097
-0.742309
-0.741522
-0.740738
-0.739955
-0.739173
-0.738393
-0.737615
-0.736839
-0.736064
-0.735291
-0.734519
-0.733750
-0.732981
-0.732215
-0.731449
-0.730686
-0.729924
-0.729164
-0.728405
-0.727648
-0.726892
-0.726138
-0.725386
-0.724635
-0.723885
-0.723138
-0.722391
-0.721647
-0.720903
-0.720162
-0.719422
-0.718683
-0.717946
-0.717210
-0.716476
-0.715744
-0.715013
-0.714283
-0.713555
-0.712828
-0.712103
-0.711379
-0.710657
-0.709937
-0.709217
-0.708499
-0.707783
-0.707068
-0.706355
-0.705643
-0.704932
-0.704223
-0.703515
-0.702809
-0.702104
-0.701400
-0.700698
-0.699998
-0.699298
-0.698600
-0.697904
-0.697209
-0.696515
-0.695823
-0.695132
-0.694442
-0.693754
-0.693067
-0.692381
-0.691697
-0.691014
-0.690333
-0.689653
-0.688974
-0.688297
-0.687621
-0.686946
-0.686272
-0.685600
-0.684929
-0.684260
-0.683592
-0.682925
-0.682259
-0.681595
-0.680932
-0.680270
-0.679610
-0.678950
-0.678292
-0.677636
-0.676981
-0.676326
-0.675674
-0.675022
-0.674372
-0.673723
-0.673075
-0.672428
-0.671783
-0.671139
-0.670496
-0.669855
-0.669214
-0.668575
-0.667937
-0.667300
-0.666665
-0.666030
-0.665397
-0.664765
-0.664135
-0.663505
-0.662877
-0.662250
-0.661624
-0.660999
-0.660376
-0.659753
-0.659132
-0.658512
-0.657893
-0.657275
-0.656659
-0.656043
-0.655429
-0.654816
-0.654204
-0.653593
-0.652983
-0.652375
-0.651767
-0.651161
-0.650556
-0.649952
-0.649349
-0.648747
-0.648147
-0.647547
-0.646948
-0.646351
-0.645755
-0.645160
-0.644566
-0.643973
-0.643381
-0.642790
-0.642200
-0.641612
-0.641024
-0.640438
-0.639852
-0.639268
-0.638685
-0.638102
-0.637521
-0.636941
-0.636362
-0.635784
-0.635207
-0.634631
-0.634057
-0.633483
-0.632910
-0.632338
-0.631768
-0.631198
-0.630629
-0.630062
-0.629495
-0.628929
-0.628365
-0.627801
-0.627239
-0.626677
-0.626117
-0.625557
-0.624999
-0.624441
-0.623885
-0.623329
-0.622774
-0.622221
-0.621668
-0.621117
-0.620566
-0.620016
-0.619468
-0.618920
-0.618373
-0.617828
-0.617283
-0.616739
-0.616196
-0.615654
-0.615113
-0.614573
-0.614034
-0.613496
-0.612959
-0.612422
-0.611887
-0.611353
-0.610819
-0.610287
-0.609755
-0.609224
-0.608695
-0.608166
-0.607638
-0.607111
-0.606585
-0.606059
-0.605535
-0.605012
-0.604489
-0.603968
-0.603447
-0.602927
-0.602409
-0.601891
-0.601374
-0.600857
-0.600342
-0.599828
-0.599314
-0.598801
-0.598290
-0.597779
-0.597269
-0.596759
-0.596251
-0.595744
-0.595237
-0.594731
</radial_potential>
<radial_function>
0.000000e+00
4.448094e-06
1.779131e-05
4.002646e-05
7.114821e-05
1.111499e-04
1.600237e-04
2.177585e-04
2.843417e-04
3.597589e-04
4.439935e-04
5.370271e-04
6.388395e-04
7.494082e-04
8.687091e-04
9.967160e-04
1.133401e-03
1.278733e-03
1.432682e-03
1.595212e-03
1.766288e-03
1.945873e-03
2.133926e-03
2.330405e-03
2.535267e-03
2.748467e-03
2.969956e-03
3.199685e-03
3.437604e-03
3.683657e-03
3.937791e-03
4.199949e-03
4.470069e-03
4.748093e-03
5.033957e-03
5.327596e-03
5.628944e-03
5.937932e-03
6.254490e-03
6.578545e-03
6.910024e-03
7.248850e-03
7.594947e-03
7.948235e-03
8.308632e-03
8.676056e-03
9.050423e-03
9.431647e-03
9.819639e-03
1.021431e-02
1.061557e-02
1.102333e-02
1.143748e-02
1.185795e-02
1.228462e-02
1.271740e-02
1.315620e-02
1.360091e-02
1.405142e-02
1.450764e-02
1.496947e-02
1.543678e-02
1.590949e-02
1.638747e-02
1.687063e-02
1.735885e-02
1.785203e-02
1.835004e-02
1.885279e-02
1.936015e-02
1.987202e-02
2.038828e-02
2.090882e-02
2.143352e-02
2.196227e-02
2.249495e-02
2.303146e-02
2.357167e-02
2.411548e-02
2.466276e-02
2.521341e-02
2.576730e-02
2.632433e-02
2.688439e-02
2.744735e-02
2.801311e-02
2.858156e-02
2.915259e-02
2.972609e-02
3.030195e-02
3.088006e-02
3.146032e-02
3.204261e-02
3.262685e-02
3.321293e-02
3.380074e-02
3.439019e-02
3.498117e-02
3.557360e-02
3.616739e-02
3.676243e-02
3.735863e-02
3.795592e-02
3.855421e-02
3.915340e-02
3.975343e-02
4.035421e-02
4.095566e-02
4.155771e-02
4.216029e-02
4.276333e-02
4.336676e-02
4.397053e-02
4.457456e-02
4.517880e-02
4.578319e-02
4.638769e-02
4.699224e-02
4.759679e-02
4.820130e-02
4.880573e-02
4.941005e-02
5.001420e-02
5.061818e-02
5.122193e-02
5.182545e-02
5.242869e-02
5.303166e-02
5.363431e-02
5.423665e-02
5.483866e-02
5.544033e-02
5.604166e-02
5.664264e-02
5.724327e-02
5.784355e-02
5.844349e-02
5.904310e-02
5.964239e-02
6.024136e-02
6.084004e-02
6.143845e-02
6.203659e-02
6.263450e-02
6.323219e-02
6.382970e-02
6.442705e-02
6.502426e-02
6.562138e-02
6.621843e-02
6.681545e-02
6.741248e-02
6.800954e-02
6.860668e-02
6.920393e-02
6.980133e-02
7.039893e-02
7.099676e-02
7.159486e-02
7.219327e-02
7.279203e-02
7.339118e-02
7.399076e-02
7.459080e-02
7.519135e-02
7.579243e-02
7.639409e-02
7.699634e-02
7.759923e-02
7.820279e-02
7.880703e-02
7.941198e-02
8.001765e-02
8.062408e-02
8.123127e-02
8.183923e-02
8.244797e-02
8.305750e-02
8.366783e-02
8.427896e-02
8.489089e-02
8.550362e-02
8.611714e-02
8.673146e-02
8.734657e-02
8.796246e-02
8.857913e-02
8.919656e-02
8.981476e-02
9.043369e-02
9.105337e-02
9.167376e-02
9.229487e-02
9.291667e-02
9.353915e-02
9.416230e-02
9.478610e-02
9.541053e-02
9.603558e-02
9.666123e-02
9.728746e-02
9.791426e-02
9.854161e-02
9.916949e-02
9.979789e-02
1.004268e-01
1.010561e-01
1.016860e-01
1.023163e-01
1.029470e-01
1.035781e-01
1.042096e-01
1.048414e-01
1.054737e-01
1.061062e-01
1.067391e-01
1.073723e-01
1.080059e-01
1.086396e-01
1.092737e-01
1.099080e-01
1.105425e-01
1.111773e-01
1.118123e-01
1.124475e-01
1.130828e-01
1.137184e-01
1.143541e-01
1.149900e-01
1.156261e-01
1.162623e-01
1.168986e-01
1.175351e-01
1.181717e-01
1.188084e-01
1.194452e-01
1.200822e-01
1.207193e-01
1.213565e-01
1.219938e-01
1.226312e-01
1.232687e-01
1.239064e-01
1.245442e-01
1.251821e-01
1.258201e-01
1.264583e-01
1.270967e-01
1.277351e-01
1.283738e-01
1.290126e-01
1.296516e-01
1.302908e-01
1.309302e-01
1.315698e-01
1.322097e-01
1.328498e-01
1.334902e-01
1.341308e-01
1.347718e-01
1.354131e-01
1.360547e-01
1.366967e-01
1.373391e-01
1.379819e-01
1.386251e-01
1.392688e-01
1.399129e-01
1.405576e-01
1.412028e-01
1.418486e-01
1.424950e-01
1.431420e-01
1.437896e-01
1.444379e-01
1.450870e-01
1.457368e-01
1.463873e-01
1.470387e-01
1.476910e-01
1.483441e-01
1.489981e-01
1.496532e-01
1.503092e-01
1.509662e-01
1.516243e-01
1.522835e-01
1.529439e-01
1.536055e-01
1.542683e-01
1.549323e-01
1.555977e-01
1.562645e-01
1.569326e-01
1.576022e-01
1.582733e-01
1.589459e-01
1.596200e-01
1.602958e-01
1.609733e-01
1.616524e-01
1.623334e-01
1.630161e-01
1.637006e-01
1.643871e-01
1.650755e-01
1.657658e-01
1.664582e-01
1.671527e-01
1.678493e-01
1.685481e-01
1.692491e-01
1.699523e-01
1.706579e-01
1.713658e-01
1.720762e-01
1.727890e-01
1.735043e-01
1.742221e-01
1.749426e-01
1.756657e-01
1.763916e-01
1.771201e-01
1.778515e-01
1.785857e-01
1.793228e-01
1.800628e-01
1.808059e-01
1.815519e-01
1.823011e-01
1.830534e-01
1.838088e-01
1.845676e-01
1.853295e-01
1.860948e-01
1.868635e-01
1.876356e-01
1.884112e-01
1.891903e-01
1.899730e-01
1.907593e-01
1.915492e-01
1.923428e-01
1.931403e-01
1.939415e-01
1.947465e-01
1.955555e-01
1.963684e-01
1.971853e-01
1.980063e-01
1.988313e-01
1.996605e-01
2.004938e-01
2.013314e-01
2.021733e-01
2.030194e-01
2.038700e-01
2.047250e-01
2.055844e-01
2.064483e-01
2.073168e-01
2.081899e-01
2.090677e-01
2.099501e-01
2.108373e-01
2.117293e-01
2.126261e-01
2.135278e-01
2.144344e-01
2.153460e-01
2.162626e-01
2.171843e-01
2.181110e-01
2.190430e-01
2.199801e-01
2.209225e-01
2.218702e-01
2.228233e-01
2.237817e-01
2.247456e-01
2.257150e-01
2.266899e-01
2.276703e-01
2.286564e-01
2.296482e-01
2.306457e-01
2.316489e-01
2.326580e-01
2.336729e-01
2.346937e-01
2.357204e-01
2.367532e-01
2.377920e-01
2.388369e-01
2.398880e-01
2.409452e-01
2.420087e-01
2.430785e-01
2.441546e-01
2.452370e-01
2.463259e-01
2.474213e-01
2.485232e-01
2.496317e-01
2.507468e-01
2.518686e-01
2.529971e-01
2.541323e-01
2.552744e-01
2.564234e-01
2.575792e-01
2.587421e-01
2.599119e-01
2.610889e-01
2.622729e-01
2.634641e-01
2.646626e-01
2.658683e-01
2.670813e-01
2.683017e-01
2.695296e-01
2.707649e-01
2.720077e-01
2.732581e-01
2.745162e-01
0.000000e+00
0.000000e+00
0.000000e+00
0.000000e+00
0.000000e+00
0.000000e+00
0.000000e+00
0.000000e+00
0.000000e+00
0.000000e+00
0.000000e+00
0.000000e+00
0.000000e+00
0.000000e+00
0.000000e+00
0.000000e+00
0.000000e+00
0.000000e+00
0.000000e+00
0.000000e+00
0.000000e+00
0.000000e+00
0.000000e+00
0.000000e+00
0.000000e+00
0.000000e+00
0.000000e+00
0.000000e+00
0.000000e+00
0.000000e+00
0.000000e+00
0.000000e+00
0.000000e+00
0.000000e+00
0.000000e+00
0.000000e+00
0.000000e+00
0.000000e+00
0.000000e+00
0.000000e+00
0.000000e+00
0.000000e+00
0.000000e+00
0.000000e+00
0.000000e+00
0.000000e+00
0.000000e+00
0.000000e+00
0.000000e+00
0.000000e+00
0.000000e+00
0.000000e+00
0.000000e+00
0.000000e+00
0.000000e+00
0.000000e+00
0.000000e+00
0.000000e+00
0.000000e+00
0.000000e+00
0.000000e+00
0.000000e+00
0.000000e+00
0.000000e+00
0.000000e+00
0.000000e+00
0.000000e+00
0.000000e+00
0.000000e+00
0.000000e+00
0.000000e+00
0.000000e+00
0.000000e+00
0.000000e+00
0.000000e+00
0.000000e+00
0.000000e+00
0.000000e+00
0.000000e+00
0.000000e+00
0.000000e+00
0.000000e+00
0.000000e+00
0.000000e+00
0.000000e+00
0.000000e+00
0.000000e+00
0.000000e+00
0.000000e+00
0.000000e+00
0.000000e+00
0.000000e+00
0.000000e+00
0.000000e+00
0.000000e+00
0.000000e+00
0.000000e+00
0.000000e+00
0.000000e+00
0.000000e+00
0.000000e+00
0.000000e+00
0.000000e+00
0.000000e+00
0.000000e+00
0.000000e+00
0.000000e+00
0.000000e+00
0.000000e+00
0.000000e+00
0.000000e+00
0.000000e+00
0.000000e+00
0.000000e+00
0.000000e+00
0.000000e+00
0.000000e+00
0.000000e+00
0.000000e+00
0.000000e+00
0.000000e+00
0.000000e+00
0.000000e+00
0.000000e+00
0.000000e+00
0.000000e+00
0.000000e+00
0.000000e+00
0.000000e+00
0.000000e+00
0.000000e+00
0.000000e+00
0.000000e+00
0.000000e+00
0.000000e+00
0.000000e+00
0.000000e+00
0.000000e+00
0.000000e+00
0.000000e+00
0.000000e+00
0.000000e+00
0.000000e+00
0.000000e+00
0.000000e+00
0.000000e+00
0.000000e+00
0.000000e+00
0.000000e+00
0.000000e+00
0.000000e+00
0.000000e+00
0.000000e+00
0.000000e+00
0.000000e+00
0.000000e+00
0.000000e+00
0.000000e+00
0.000000e+00
0.000000e+00
0.000000e+00
0.000000e+00
0.000000e+00
0.000000e+00
0.000000e+00
0.000000e+00
0.000000e+00
0.000000e+00
0.000000e+00
0.000000e+00
0.000000e+00
0.000000e+00
0.000000e+00
0.000000e+00
0.000000e+00
0.000000e+00
0.000000e+00
0.000000e+00
0.000000e+00
0.000000e+00
0.000000e+00
0.000000e+00
0.000000e+00
0.000000e+00
0.000000e+00
0.000000e+00
0.000000e+00
0.000000e+00
0.000000e+00
0.000000e+00
0.000000e+00
0.000000e+00
0.000000e+00
0.000000e+00
0.000000e+00
0.000000e+00
0.000000e+00
0.000000e+00
0.000000e+00
0.000000e+00
0.000000e+00
0.000000e+00
0.000000e+00
0.000000e+00
0.000000e+00
0.000000e+00
0.000000e+00
0.000000e+00
0.000000e+00
0.000000e+00
0.000000e+00
0.000000e+00
0.000000e+00
0.000000e+00
0.000000e+00
0.000000e+00
0.000000e+00
0.000000e+00
0.000000e+00
0.000000e+00
0.000000e+00
0.000000e+00
0.000000e+00
0.000000e+00
0.000000e+00
0.000000e+00
0.000000e+00
0.000000e+00
0.000000e+00
0.000000e+00
0.000000e+00
0.000000e+00
0.000000e+00
0.000000e+00
0.000000e+00
0.000000e+00
0.000000e+00
0.000000e+00
0.000000e+00
0.000000e+00
0.000000e+00
0.000000e+00
0.000000e+00
0.000000e+00
0.000000e+00
0.000000e+00
0.000000e+00
0.000000e+00
0.000000e+00
0.000000e+00
0.000000e+00
0.000000e+00
0.000000e+00
0.000000e+00
0.000000e+00
0.000000e+00
0.000000e+00
0.000000e+00
0.000000e+00
0.000000e+00
0.000000e+00
0.000000e+00
0.000000e+00
0.000000e+00
0.000000e+00
0.000000e+00
0.000000e+00
0.000000e+00
0.000000e+00
0.000000e+00
0.000000e+00
0.000000e+00
0.000000e+00
0.000000e+00
0.000000e+00
0.000000e+00
0.000000e+00
0.000000e+00
0.000000e+00
0.000000e+00
0.000000e+00
0.000000e+00
0.000000e+00
0.000000e+00
0.000000e+00
0.000000e+00
0.000000e+00
0.000000e+00
0.000000e+00
0.000000e+00
0.000000e+00
0.000000e+00
0.000000e+00
0.000000e+00
0.000000e+00
0.000000e+00
0.000000e+00
0.000000e+00
0.000000e+00
0.000000e+00
0.000000e+00
0.000000e+00
0.000000e+00
0.000000e+00
0.000000e+00
0.000000e+00
0.000000e+00
0.000000e+00
0.000000e+00
0.000000e+00
0.000000e+00
0.000000e+00
0.000000e+00
0.000000e+00
0.000000e+00
0.000000e+00
0.000000e+00
0.000000e+00
0.000000e+00
0.000000e+00
0.000000e+00
0.000000e+00
0.000000e+00
0.000000e+00
0.000000e+00
0.000000e+00
0.000000e+00
0.000000e+00
0.000000e+00
0.000000e+00
0.000000e+00
0.000000e+00
0.000000e+00
0.000000e+00
0.000000e+00
0.000000e+00
0.000000e+00
0.000000e+00
0.000000e+00
0.000000e+00
0.000000e+00
0.000000e+00
0.000000e+00
0.000000e+00
0.000000e+00
0.000000e+00
0.000000e+00
0.000000e+00
0.000000e+00
0.000000e+00
0.000000e+00
0.000000e+00
0.000000e+00
0.000000e+00
0.000000e+00
0.000000e+00
0.000000e+00
0.000000e+00
0.000000e+00
0.000000e+00
0.000000e+00
0.000000e+00
0.000000e+00
0.000000e+00
0.000000e+00
0.000000e+00
0.000000e+00
0.000000e+00
0.000000e+00
0.000000e+00
0.000000e+00
0.000000e+00
0.000000e+00
0.000000e+00
0.000000e+00
0.000000e+00
0.000000e+00
0.000000e+00
0.000000e+00
0.000000e+00
0.000000e+00
0.000000e+00
0.000000e+00
0.000000e+00
0.000000e+00
0.000000e+00
0.000000e+00
0.000000e+00
0.000000e+00
0.000000e+00
0.000000e+00
0.000000e+00
0.000000e+00
0.000000e+00
0.000000e+00
0.000000e+00
0.000000e+00
0.000000e+00
0.000000e+00
0.000000e+00
0.000000e+00
0.000000e+00
0.000000e+00
0.000000e+00
0.000000e+00
0.000000e+00
0.000000e+00
0.000000e+00
0.000000e+00
0.000000e+00
0.000000e+00
0.000000e+00
0.000000e+00
0.000000e+00
0.000000e+00
0.000000e+00
0.000000e+00
0.000000e+00
0.000000e+00
0.000000e+00
0.000000e+00
0.000000e+00
0.000000e+00
0.000000e+00
0.000000e+00
0.000000e+00
0.000000e+00
0.000000e+00
0.000000e+00
0.000000e+00
0.000000e+00
0.000000e+00
0.000000e+00
0.000000e+00
0.000000e+00
0.000000e+00
0.000000e+00
0.000000e+00
0.000000e+00
0.000000e+00
0.000000e+00
0.000000e+00
0.000000e+00
0.000000e+00
0.000000e+00
0.000000e+00
0.000000e+00
0.000000e+00
0.000000e+00
0.000000e+00
0.000000e+00
0.000000e+00
0.000000e+00
0.000000e+00
0.000000e+00
0.000000e+00
0.000000e+00
0.000000e+00
0.000000e+00
0.000000e+00
0.000000e+00
0.000000e+00
0.000000e+00
0.000000e+00
0.000000e+00
0.000000e+00
0.000000e+00
0.000000e+00
0.000000e+00
0.000000e+00
0.000000e+00
0.000000e+00
0.000000e+00
0.000000e+00
0.000000e+00
0.000000e+00
0.000000e+00
0.000000e+00
0.000000e+00
0.000000e+00
0.000000e+00
0.000000e+00
0.000000e+00
0.000000e+00
0.000000e+00
0.000000e+00
0.000000e+00
0.000000e+00
0.000000e+00
0.000000e+00
0.000000e+00
0.000000e+00
0.000000e+00
0.000000e+00
0.000000e+00
0.000000e+00
0.000000e+00
0.000000e+00
0.000000e+00
0.000000e+00
0.000000e+00
0.000000e+00
0.000000e+00
0.000000e+00
0.000000e+00
0.000000e+00
0.000000e+00
0.000000e+00
0.000000e+00
0.000000e+00
0.000000e+00
0.000000e+00
0.000000e+00
0.000000e+00
0.000000e+00
0.000000e+00
0.000000e+00
0.000000e+00
0.000000e+00
0.000000e+00
0.000000e+00
0.000000e+00
0.000000e+00
0.000000e+00
0.000000e+00
0.000000e+00
0.000000e+00
0.000000e+00
0.000000e+00
0.000000e+00
0.000000e+00
0.000000e+00
0.000000e+00
0.000000e+00
0.000000e+00
0.000000e+00
0.000000e+00
0.000000e+00
0.000000e+00
0.000000e+00
0.000000e+00
0.000000e+00
0.000000e+00
0.000000e+00
0.000000e+00
0.000000e+00
0.000000e+00
0.000000e+00
0.000000e+00
0.000000e+00
0.000000e+00
0.000000e+00
0.000000e+00
0.000000e+00
0.000000e+00
0.000000e+00
0.000000e+00
0.000000e+00
0.000000e+00
0.000000e+00
0.000000e+00
0.000000e+00
0.000000e+00
0.000000e+00
0.000000e+00
0.000000e+00
0.000000e+00
0.000000e+00
0.000000e+00
0.000000e+00
0.000000e+00
0.000000e+00
0.000000e+00
0.000000e+00
0.000000e+00
0.000000e+00
0.000000e+00
0.000000e+00
0.000000e+00
0.000000e+00
0.000000e+00
0.000000e+00
0.000000e+00
0.000000e+00
0.000000e+00
0.000000e+00
0.000000e+00
0.000000e+00
0.000000e+00
0.000000e+00
0.000000e+00
0.000000e+00
0.000000e+00
0.000000e+00
0.000000e+00
0.000000e+00
0.000000e+00
0.000000e+00
0.000000e+00
0.000000e+00
0.000000e+00
0.000000e+00
0.000000e+00
0.000000e+00
0.000000e+00
0.000000e+00
0.000000e+00
0.000000e+00
0.000000e+00
0.000000e+00
0.000000e+00
0.000000e+00
0.000000e+00
0.000000e+00
0.000000e+00
0.000000e+00
0.000000e+00
0.000000e+00
0.000000e+00
0.000000e+00
0.000000e+00
0.000000e+00
0.000000e+00
0.000000e+00
0.000000e+00
0.000000e+00
0.000000e+00
0.000000e+00
0.000000e+00
0.000000e+00
0.000000e+00
0.000000e+00
0.000000e+00
0.000000e+00
0.000000e+00
0.000000e+00
0.000000e+00
0.000000e+00
0.000000e+00
0.000000e+00
0.000000e+00
0.000000e+00
0.000000e+00
0.000000e+00
0.000000e+00
0.000000e+00
0.000000e+00
0.000000e+00
0.000000e+00
0.000000e+00
0.000000e+00
0.000000e+00
0.000000e+00
0.000000e+00
0.000000e+00
0.000000e+00
0.000000e+00
0.000000e+00
0.000000e+00
0.000000e+00
0.000000e+00
0.000000e+00
0.000000e+00
0.000000e+00
0.000000e+00
0.000000e+00
0.000000e+00
0.000000e+00
0.000000e+00
0.000000e+00
0.000000e+00
0.000000e+00
0.000000e+00
0.000000e+00
0.000000e+00
0.000000e+00
0.000000e+00
0.000000e+00
0.000000e+00
0.000000e+00
0.000000e+00
0.000000e+00
0.000000e+00
0.000000e+00
0.000000e+00
0.000000e+00
0.000000e+00
0.000000e+00
0.000000e+00
0.000000e+00
0.000000e+00
0.000000e+00
0.000000e+00
0.000000e+00
0.000000e+00
0.000000e+00
0.000000e+00
0.000000e+00
0.000000e+00
0.000000e+00
0.000000e+00
0.000000e+00
0.000000e+00
0.000000e+00
0.000000e+00
0.000000e+00
0.000000e+00
0.000000e+00
0.000000e+00
0.000000e+00
0.000000e+00
0.000000e+00
0.000000e+00
0.000000e+00
0.000000e+00
0.000000e+00
0.000000e+00
0.000000e+00
0.000000e+00
0.000000e+00
0.000000e+00
0.000000e+00
0.000000e+00
0.000000e+00
0.000000e+00
0.000000e+00
0.000000e+00
0.000000e+00
0.000000e+00
0.000000e+00
0.000000e+00
0.000000e+00
0.000000e+00
0.000000e+00
0.000000e+00
0.000000e+00
0.000000e+00
0.000000e+00
0.000000e+00
0.000000e+00
0.000000e+00
0.000000e+00
0.000000e+00
0.000000e+00
0.000000e+00
0.000000e+00
0.000000e+00
0.000000e+00
0.000000e+00
0.000000e+00
0.000000e+00
0.000000e+00
0.000000e+00
</radial_function>
</projector>
</norm_conserving_pseudopotential>
</fpmd:species>
